Workbook

Sheet Paramètres
A1: Budget Food truck
B3: Année | C3: 2025 | D3: =C3+1 -> 2026 | E3: =D3+1 -> 2027
B4: Prix de vente repas moyen TTC | C4: 15 | D4: =C4*1.05 -> 15.75 | E4: =D4*1.05 -> 16.5375
B5: Achat de MP | C5: 0.34 | D5: 0.35 | E5: 0.36
B6: Achat Boissons | C6: 0.24 | D6: 0.25 | E6: 0.26
B7: Prix emballages/vente | C7: 0.27 | D7: =C7 -> 0.27 | E7: =D7 -> 0.27
B8: NB ventes/jour | C8: 50 | D8: =C8*1.1 -> 55 | E8: =D8*1.05 -> 57.75
B9: Distance journalière (km) | C9: 50 | D9: 50 | E9: 50
B10: Coût occupation temporaire | C10: 150 | D10: =C10*1.05 -> 157.5 | E10: =D10*1.05 -> 165.375
B11: Coût carburant / 100 km | C11: 7 | D11: =C11*1.1 -> 7.7 | E11: =D11*1.1 -> 8.47
B12: Coût/km | C12: =C11/100 -> 0.07 | D12: =D11/100 -> 0.077 | E12: =E11/100 -> 0.0847
B13: Achat véhicule | C13: ='Plan de financement initial'!D23 -> 39000
B14: Mois de mise en service | C14: Janvier
B15: Montant emprunt | C15: ='Plan de financement initial'!H30 -> 37000
B16: Taux | C16: 0.035
B17: Durée (ans) | C17: 5

Sheet Trésorerie année 1
A1: Budget de trésorerie | B1: =Paramètres!$C$3 -> 2025
A2: Régime fiscal EURL
A3: Trésorerie début de mois | B3: 0 | C3: =B51 -> 10461.905 | D3: =C51 -> 11693.811 | E3: =D51 -> 13235.716 | F3: =E51 -> 14587.622 | G3: =F51 -> 15939.527 | H3: =G51 -> 17481.433 | I3: =H51 -> 19393.338 | J3: =I51 -> 20935.243 | ... M3: =L51 -> 24254.494
B5: Janvier | C5: Février | D5: Mars | E5: Avril | F5: Mai | G5: Juin | H5: Juillet | I5: Août | J5: Septembre | K5: Octobre | L5: Novembre | M5: Décembre | O5: TOTAL
A6: Nb de jours ouvrables | B6: =NETWORKDAYS(DATE(Paramètres!$C$3,COLUMN()-1,1),EOMONTH(DATE(Paramètres!$C$3,COLUMN()-1,1),0)) -> 23 | C6: =NETWORKDAYS(DATE(Paramètres!$C$3,COLUMN()-1,1),EOMONTH(DATE(Paramètres!$C$3,COLUMN()-1,1),0)) -> 20 | D6: =NETWORKDAYS(DATE(Paramètres!$C$3,COLUMN()-1,1),EOMONTH(DATE(Paramètres!$C$3,COLUMN()-1,1),0)) -> 21 | E6: =NETWORKDAYS(DATE(Paramètres!$C$3,COLUMN()-1,1),EOMONTH(DATE(Paramètres!$C$3,COLUMN()-1,1),0)) -> 22 | F6: =NETWORKDAYS(DATE(Paramètres!$C$3,COLUMN()-1,1),EOMONTH(DATE(Paramètres!$C$3,COLUMN()-1,1),0)) -> 22 | G6: =NETWORKDAYS(DATE(Paramètres!$C$3,COLUMN()-1,1),EOMONTH(DATE(Paramètres!$C$3,COLUMN()-1,1),0)) -> 21 | H6: =NETWORKDAYS(DATE(Paramètres!$C$3,COLUMN()-1,1),EOMONTH(DATE(Paramètres!$C$3,COLUMN()-1,1),0)) -> 23 | I6: =NETWORKDAYS(DATE(Paramètres!$C$3,COLUMN()-1,1),EOMONTH(DATE(Paramètres!$C$3,COLUMN()-1,1),0)) -> 21 | ... M6: =NETWORKDAYS(DATE(Paramètres!$C$3,COLUMN()-1,1),EOMONTH(DATE(Paramètres!$C$3,COLUMN()-1,1),0)) -> 23 | O6: =SUM(B6:M6) -> 261
A7: Ventes repas | B7: =(Paramètres!$C$8*Paramètres!$C$4*'Trésorerie année 1'!B6) -> 17250 | C7: =(Paramètres!$C$8*Paramètres!$C$4*'Trésorerie année 1'!C6) -> 15000 | D7: =(Paramètres!$C$8*Paramètres!$C$4*'Trésorerie année 1'!D6) -> 15750 | E7: =(Paramètres!$C$8*Paramètres!$C$4*'Trésorerie année 1'!E6) -> 16500 | F7: =(Paramètres!$C$8*Paramètres!$C$4*'Trésorerie année 1'!F6) -> 16500 | G7: =(Paramètres!$C$8*Paramètres!$C$4*'Trésorerie année 1'!G6) -> 15750 | H7: =(Paramètres!$C$8*Paramètres!$C$4*'Trésorerie année 1'!H6) -> 17250 | I7: =(Paramètres!$C$8*Paramètres!$C$4*'Trésorerie année 1'!I6) -> 15750 | ... M7: =(Paramètres!$C$8*Paramètres!$C$4*'Trésorerie année 1'!M6) -> 17250 | O7: =SUM(B7:M7) -> 195750
A8: Ventes Boissons | B8: =Paramètres!$C$8*'Trésorerie année 1'!B6*Paramètres!$C$6*3 -> 828 | C8: =Paramètres!$C$8*'Trésorerie année 1'!C6*Paramètres!$C$6*3 -> 720 | D8: =Paramètres!$C$8*'Trésorerie année 1'!D6*Paramètres!$C$6*3 -> 756 | E8: =Paramètres!$C$8*'Trésorerie année 1'!E6*Paramètres!$C$6*3 -> 792 | F8: =Paramètres!$C$8*'Trésorerie année 1'!F6*Paramètres!$C$6*3 -> 792 | G8: =Paramètres!$C$8*'Trésorerie année 1'!G6*Paramètres!$C$6*3 -> 756 | H8: =Paramètres!$C$8*'Trésorerie année 1'!H6*Paramètres!$C$6*3 -> 828 | I8: =Paramètres!$C$8*'Trésorerie année 1'!I6*Paramètres!$C$6*3 -> 756 | ... M8: =Paramètres!$C$8*'Trésorerie année 1'!M6*Paramètres!$C$6*3 -> 828 | O8: =SUM(B8:M8) -> 9396
A9: Apport personnel - associés | B9: ='Plan de financement initial'!H7 -> 22000 | O9: =SUM(B9:M9) -> 22000
A10: Prêts et financements | B10: =Paramètres!$C$15 -> 37000 | O10: =SUM(B10:M10) -> 37000
A11: Aides & Subventions | B11: ='Plan de financement initial'!H16+'Plan de financement initial'!H19+'Plan de financement initial'!H24 -> 0 | O11: =SUM(B11:M11) -> 0
A12: ENCAISSEMENTS | B12: =SUM(B7:B11) -> 77078 | C12: =SUM(C7:C11) -> 15720 | D12: =SUM(D7:D11) -> 16506 | E12: =SUM(E7:E11) -> 17292 | F12: =SUM(F7:F11) -> 17292 | G12: =SUM(G7:G11) -> 16506 | H12: =SUM(H7:H11) -> 18078 | I12: =SUM(I7:I11) -> 16506 | ... M12: =SUM(M7:M11) -> 18078 | O12: =SUM(B12:M12) -> 264146 | P12: =IF(O12=SUM(O7:O11),"ok","non") -> ok
A14: Immobilisations incorporelles | B14: ='Plan de financement initial'!D15+'Plan de financement initial'!D7 -> 2000 | O14: =SUM(B14:M14) -> 2000
A15: Immobilisations corporelles | B15: =Paramètres!$C$13+'Plan de financement initial'!D25 -> 48000 | C15: =IF(C5=Paramètres!$C$14,Paramètres!$C$13,0) -> 0 | D15: =IF(D5=Paramètres!$C$14,Paramètres!$C$13,0) -> 0 | E15: =IF(E5=Paramètres!$C$14,Paramètres!$C$13,0) -> 0 | F15: 0 | G15: =IF(G5=Paramètres!$C$14,Paramètres!$C$13,0) -> 0 | H15: =IF(H5=Paramètres!$C$14,Paramètres!$C$13,0) -> 0 | I15: =IF(I5=Paramètres!$C$14,Paramètres!$C$13,0) -> 0 | J15: =IF(J5=Paramètres!$C$14,Paramètres!$C$13,0) -> 0 | K15: =IF(K5=Paramètres!$C$14,Paramètres!$C$13,0) -> 0 | L15: =IF(L5=Paramètres!$C$14,Paramètres!$C$13,0) -> 0 | M15: =IF(M5=Paramètres!$C$14,Paramètres!$C$13,0) -> 0 | O15: =SUM(B15:M15) -> 48000
A16: IMMOBILISATIONS | B16: =SUM(B14:B15) -> 50000 | C16: =SUM(C14:C15) -> 0 | D16: =SUM(D14:D15) -> 0 | E16: =SUM(E14:E15) -> 0 | F16: =SUM(F14:F15) -> 0 | G16: =SUM(G14:G15) -> 0 | H16: =SUM(H14:H15) -> 0 | I16: =SUM(I14:I15) -> 0 | ... M16: =SUM(M14:M15) -> 0 | O16: =SUM(B16:M16) -> 50000 | P16: =IF(O16=SUM(O14:O15),"ok","non") -> ok
A18: Achats de MP | B18: =B7*Paramètres!$C$5 -> 5865 | C18: =C7*Paramètres!$C$5 -> 5100 | D18: =D7*Paramètres!$C$5 -> 5355 | E18: =E7*Paramètres!$C$5 -> 5610 | F18: =F7*Paramètres!$C$5 -> 5610 | G18: =G7*Paramètres!$C$5 -> 5355 | H18: =H7*Paramètres!$C$5 -> 5865 | I18: =I7*Paramètres!$C$5 -> 5355 | ... M18: =M7*Paramètres!$C$5 -> 5865 | O18: =SUM(B18:M18) -> 66555
A19: Emballages | B19: =Paramètres!$C$7*Paramètres!$C$8*'Trésorerie année 1'!B6 -> 310.5 | C19: =Paramètres!$C$7*Paramètres!$C$8*'Trésorerie année 1'!C6 -> 270 | D19: =Paramètres!$C$7*Paramètres!$C$8*'Trésorerie année 1'!D6 -> 283.5 | E19: =Paramètres!$C$7*Paramètres!$C$8*'Trésorerie année 1'!E6 -> 297 | F19: =Paramètres!$C$7*Paramètres!$C$8*'Trésorerie année 1'!F6 -> 297 | G19: =Paramètres!$C$7*Paramètres!$C$8*'Trésorerie année 1'!G6 -> 283.5 | H19: =Paramètres!$C$7*Paramètres!$C$8*'Trésorerie année 1'!H6 -> 310.5 | I19: =Paramètres!$C$7*Paramètres!$C$8*'Trésorerie année 1'!I6 -> 283.5 | ... M19: =Paramètres!$C$7*Paramètres!$C$8*'Trésorerie année 1'!M6 -> 310.5 | O19: =SUM(B19:M19) -> 3523.5
A20: Carburant | B20: =Paramètres!$C$9*Paramètres!$C$12*'Trésorerie année 1'!B6 -> 80.5 | C20: =Paramètres!$C$9*Paramètres!$C$12*'Trésorerie année 1'!C6 -> 70 | D20: =Paramètres!$C$9*Paramètres!$C$12*'Trésorerie année 1'!D6 -> 73.5 | E20: =Paramètres!$C$9*Paramètres!$C$12*'Trésorerie année 1'!E6 -> 77 | F20: =Paramètres!$C$9*Paramètres!$C$12*'Trésorerie année 1'!F6 -> 77 | G20: =Paramètres!$C$9*Paramètres!$C$12*'Trésorerie année 1'!G6 -> 73.5 | H20: =Paramètres!$C$9*Paramètres!$C$12*'Trésorerie année 1'!H6 -> 80.5 | I20: =Paramètres!$C$9*Paramètres!$C$12*'Trésorerie année 1'!I6 -> 73.5 | ... M20: =Paramètres!$C$9*Paramètres!$C$12*'Trésorerie année 1'!M6 -> 80.5 | O20: =SUM(B20:M20) -> 913.5
A21: Achats marchandises (boissons) | B21: =B8*Paramètres!$C$6 -> 198.72 | C21: =C8*Paramètres!$C$6 -> 172.8 | D21: =D8*Paramètres!$C$6 -> 181.44 | E21: =E8*Paramètres!$C$6 -> 190.08 | F21: =F8*Paramètres!$C$6 -> 190.08 | G21: =G8*Paramètres!$C$6 -> 181.44 | H21: =H8*Paramètres!$C$6 -> 198.72 | I21: =I8*Paramètres!$C$6 -> 181.44 | ... M21: =M8*Paramètres!$C$6 -> 198.72 | O21: =SUM(B21:M21) -> 2255.04
A22: Fluides (eau, électricité, gaz, etc.) | B22: =B7*0.05 -> 862.5 | C22: =C7*0.05 -> 750 | D22: =D7*0.05 -> 787.5 | E22: =E7*0.05 -> 825 | F22: =F7*0.05 -> 825 | G22: =G7*0.05 -> 787.5 | H22: =H7*0.05 -> 862.5 | I22: =I7*0.05 -> 787.5 | ... M22: =M7*0.05 -> 862.5 | O22: =SUM(B22:M22) -> 9787.5
A23: Frais d'emplacement (AOT) | B23: =Paramètres!$C$10*'Trésorerie année 1'!B6 -> 3450 | C23: =Paramètres!$C$10*'Trésorerie année 1'!C6 -> 3000 | D23: =Paramètres!$C$10*'Trésorerie année 1'!D6 -> 3150 | E23: =Paramètres!$C$10*'Trésorerie année 1'!E6 -> 3300 | F23: =Paramètres!$C$10*'Trésorerie année 1'!F6 -> 3300 | G23: =Paramètres!$C$10*'Trésorerie année 1'!G6 -> 3150 | H23: =Paramètres!$C$10*'Trésorerie année 1'!H6 -> 3450 | I23: =Paramètres!$C$10*'Trésorerie année 1'!I6 -> 3150 | ... M23: =Paramètres!$C$10*'Trésorerie année 1'!M6 -> 3450 | O23: =SUM(B23:M23) -> 39150
A24: Loyer local labo | B24: 500 | C24: 500 | D24: 500 | E24: 500 | F24: 500 | G24: 500 | H24: 500 | I24: 500 | J24: 500 | K24: 500 | L24: 500 | M24: 500 | O24: =SUM(B24:M24) -> 6000
A25: Frais internet-téléphone | B25: =20 -> 20 | C25: 20 | D25: 20 | E25: 20 | F25: 20 | G25: 20 | H25: 20 | I25: 20 | J25: 20 | K25: 20 | L25: 20 | M25: 20 | O25: =SUM(B25:M25) -> 240
A26: Frais logiciel TPE | B26: =(B7+B8)*0.01 -> 180.78 | C26: =(C7+C8)*0.01 -> 157.2 | D26: =(D7+D8)*0.01 -> 165.06 | E26: =(E7+E8)*0.01 -> 172.92 | F26: =(F7+F8)*0.01 -> 172.92 | G26: =(G7+G8)*0.01 -> 165.06 | H26: =(H7+H8)*0.01 -> 180.78 | I26: =(I7+I8)*0.01 -> 165.06 | ... M26: =(M7+M8)*0.01 -> 180.78 | O26: =SUM(B26:M26) -> 2051.46
A27: Fournitures diverses | B27: 700 | E27: 500 | H27: 250 | K27: 250 | O27: =SUM(B27:M27) -> 1700
A28: Entretien / Maintenance | B28: 150 | C28: 150 | D28: 150 | E28: 150 | F28: 150 | G28: 150 | H28: 150 | I28: 150 | J28: 150 | K28: 150 | L28: 150 | M28: 150 | O28: =SUM(B28:M28) -> 1800
A29: Assurances (camion, local, RC) | B29: 225 | C29: 225 | D29: 225 | E29: 225 | F29: 225 | G29: 225 | H29: 225 | I29: 225 | J29: 225 | K29: 225 | L29: 225 | M29: 225 | O29: =SUM(B29:M29) -> 2700
A30: Publicité / Communication / Mkgt | F30: 500 | J30: 500 | O30: =SUM(B30:M30) -> 1000
A31: Honoraires (prestataires divers) | B31: =100 -> 100 | C31: 100 | D31: 100 | E31: 100 | F31: 100 | G31: 100 | H31: 100 | I31: 100 | J31: 100 | K31: 100 | L31: 100 | M31: 100 | O31: =SUM(B31:M31) -> 1200
A32: Mutuelle | B32: 100 | C32: 100 | D32: 100 | E32: 100 | F32: 100 | G32: 100 | H32: 100 | I32: 100 | J32: 100 | K32: 100 | L32: 100 | M32: 100 | O32: =SUM(B32:M32) -> 1200
A33: Salaires Bruts Gérant | B33: 2200 | C33: 2200 | D33: 2200 | E33: 2200 | F33: 2200 | G33: 2200 | H33: 2200 | I33: 2200 | J33: 2200 | K33: 2200 | L33: 2200 | M33: 2200 | O33: =SUM(B33:M33) -> 26400
A34: Charges sociales patronales Gérant | B34: =B33*0.45 -> 990 | C34: =C33*0.45 -> 990 | D34: =D33*0.45 -> 990 | E34: =E33*0.45 -> 990 | F34: =F33*0.45 -> 990 | G34: =G33*0.45 -> 990 | H34: =H33*0.45 -> 990 | I34: =I33*0.45 -> 990 | ... M34: =M33*0.45 -> 990 | O34: =SUM(B34:M34) -> 11880
A35: Frais financiers (frais TC, î) | B35: 10 | C35: 10 | D35: 10 | E35: 10 | F35: 10 | G35: 10 | H35: 10 | I35: 10 | J35: 10 | K35: 10 | L35: 10 | M35: 10 | O35: =SUM(B35:M35) -> 120
A36: Échéances d'emprunt | B36: =IF(Paramètres!$C$15="",0,-PMT(Paramètres!$C$16/12,Paramètres!$C$17*12,Paramètres!$C$15)) -> 673.09456 | C36: =IF(Paramètres!$C$15="",0,-PMT(Paramètres!$C$16/12,Paramètres!$C$17*12,Paramètres!$C$15)) -> 673.09456 | D36: =IF(Paramètres!$C$15="",0,-PMT(Paramètres!$C$16/12,Paramètres!$C$17*12,Paramètres!$C$15)) -> 673.09456 | E36: =IF(Paramètres!$C$15="",0,-PMT(Paramètres!$C$16/12,Paramètres!$C$17*12,Paramètres!$C$15)) -> 673.09456 | F36: =IF(Paramètres!$C$15="",0,-PMT(Paramètres!$C$16/12,Paramètres!$C$17*12,Paramètres!$C$15)) -> 673.09456 | G36: =IF(Paramètres!$C$15="",0,-PMT(Paramètres!$C$16/12,Paramètres!$C$17*12,Paramètres!$C$15)) -> 673.09456 | H36: =IF(Paramètres!$C$15="",0,-PMT(Paramètres!$C$16/12,Paramètres!$C$17*12,Paramètres!$C$15)) -> 673.09456 | I36: =IF(Paramètres!$C$15="",0,-PMT(Paramètres!$C$16/12,Paramètres!$C$17*12,Paramètres!$C$15)) -> 673.09456 | ... M36: =IF(Paramètres!$C$15="",0,-PMT(Paramètres!$C$16/12,Paramètres!$C$17*12,Paramètres!$C$15)) -> 673.09456 | O36: =SUM(B36:M36) -> 8077.1348
A37: IS ou autres selon régime jurid | O37: =SUM(B37:M37) -> 0
A38: DECAISSEMENTS | B38: =SUM(B18:B37) -> 16616.095 | C38: =SUM(C18:C37) -> 14488.095 | D38: =SUM(D18:D37) -> 14964.095 | E38: =SUM(E18:E37) -> 15940.095 | F38: =SUM(F18:F37) -> 15940.095 | G38: =SUM(G18:G37) -> 14964.095 | H38: =SUM(H18:H37) -> 16166.095 | I38: =SUM(I18:I37) -> 14964.095 | ... M38: =SUM(M18:M37) -> 15916.095 | O38: =SUM(B38:M38) -> 186553.13 | P38: =IF(O38=SUM(O18:O37),"ok","non") -> ok
A40: TVA collectée 20% | B40: =B8/1.2*0.2*0.25 -> 34.5 | C40: =C8/1.2*0.2*0.25 -> 30 | D40: =D8/1.2*0.2*0.25 -> 31.5 | E40: =E8/1.2*0.2*0.25 -> 33 | F40: =F8/1.2*0.2*0.25 -> 33 | G40: =G8/1.2*0.2*0.25 -> 31.5 | H40: =H8/1.2*0.2*0.25 -> 34.5 | I40: =I8/1.2*0.2*0.25 -> 31.5 | ... M40: =M8/1.2*0.2*0.25 -> 34.5 | O40: =SUM(B40:M40) -> 391.5
A41: TVA Collectée 10% | B41: =B7/1.1*0.1+B8/1.1*0.1*0.75 -> 1624.6364 | C41: =C7/1.1*0.1+C8/1.1*0.1*0.75 -> 1412.7273 | D41: =D7/1.1*0.1+D8/1.1*0.1*0.75 -> 1483.3636 | E41: =E7/1.1*0.1+E8/1.1*0.1*0.75 -> 1554 | F41: =F7/1.1*0.1+F8/1.1*0.1*0.75 -> 1554 | G41: =G7/1.1*0.1+G8/1.1*0.1*0.75 -> 1483.3636 | H41: =H7/1.1*0.1+H8/1.1*0.1*0.75 -> 1624.6364 | I41: =I7/1.1*0.1+I8/1.1*0.1*0.75 -> 1483.3636 | ... M41: =M7/1.1*0.1+M8/1.1*0.1*0.75 -> 1624.6364 | O41: =SUM(B41:M41) -> 18436.091
A42: TVA collectée 5,5% | O42: =SUM(B42:M42) -> 0
A43: TVA déductible 20% | B43: =(B16/1.2*0.2)+(B19/1.2*0.2)+(B20/1.2*0.2)+(B21/1.2*0.2*0.25)+(B22/1.2*0.2)+(B25/1.2*0.2)+(B26/1.2*0.2)+(B27/1.2*0.2)+(B28/1.2*0.2)+(B30/1.2*0.2)+(B31/1.2*0.2) -> 8742.3267 | C43: =(C16/1.2*0.2)+(C19/1.2*0.2)+(C20/1.2*0.2)+(C21/1.2*0.2*0.25)+(C22/1.2*0.2)+(C25/1.2*0.2)+(C26/1.2*0.2)+(C27/1.2*0.2)+(C28/1.2*0.2)+(C30/1.2*0.2)+(C31/1.2*0.2) -> 260.06667 | D43: =(D16/1.2*0.2)+(D19/1.2*0.2)+(D20/1.2*0.2)+(D21/1.2*0.2*0.25)+(D22/1.2*0.2)+(D25/1.2*0.2)+(D26/1.2*0.2)+(D27/1.2*0.2)+(D28/1.2*0.2)+(D30/1.2*0.2)+(D31/1.2*0.2) -> 270.82 | E43: =(E16/1.2*0.2)+(E19/1.2*0.2)+(E20/1.2*0.2)+(E21/1.2*0.2*0.25)+(E22/1.2*0.2)+(E25/1.2*0.2)+(E26/1.2*0.2)+(E27/1.2*0.2)+(E28/1.2*0.2)+(E30/1.2*0.2)+(E31/1.2*0.2) -> 364.90667 | F43: =(F16/1.2*0.2)+(F19/1.2*0.2)+(F20/1.2*0.2)+(F21/1.2*0.2*0.25)+(F22/1.2*0.2)+(F25/1.2*0.2)+(F26/1.2*0.2)+(F27/1.2*0.2)+(F28/1.2*0.2)+(F30/1.2*0.2)+(F31/1.2*0.2) -> 364.90667 | G43: =(G16/1.2*0.2)+(G19/1.2*0.2)+(G20/1.2*0.2)+(G21/1.2*0.2*0.25)+(G22/1.2*0.2)+(G25/1.2*0.2)+(G26/1.2*0.2)+(G27/1.2*0.2)+(G28/1.2*0.2)+(G30/1.2*0.2)+(G31/1.2*0.2) -> 270.82 | H43: =(H16/1.2*0.2)+(H19/1.2*0.2)+(H20/1.2*0.2)+(H21/1.2*0.2*0.25)+(H22/1.2*0.2)+(H25/1.2*0.2)+(H26/1.2*0.2)+(H27/1.2*0.2)+(H28/1.2*0.2)+(H30/1.2*0.2)+(H31/1.2*0.2) -> 333.99333 | I43: =(I16/1.2*0.2)+(I19/1.2*0.2)+(I20/1.2*0.2)+(I21/1.2*0.2*0.25)+(I22/1.2*0.2)+(I25/1.2*0.2)+(I26/1.2*0.2)+(I27/1.2*0.2)+(I28/1.2*0.2)+(I30/1.2*0.2)+(I31/1.2*0.2) -> 270.82 | ... M43: =(M16/1.2*0.2)+(M19/1.2*0.2)+(M20/1.2*0.2)+(M21/1.2*0.2*0.25)+(M22/1.2*0.2)+(M25/1.2*0.2)+(M26/1.2*0.2)+(M27/1.2*0.2)+(M28/1.2*0.2)+(M30/1.2*0.2)+(M31/1.2*0.2) -> 292.32667 | O43: =SUM(B43:M43) -> 12129.953
A44: TVA Déductible 10% | O44: =SUM(B44:M44) -> 0
A45: TVA Déductible 5,5% | B45: =(B18/1.055*0.055)+(B21/1.055*0.055*0.75) -> 313.52815 | C45: =(C18/1.055*0.055)+(C21/1.055*0.055*0.75) -> 272.63318 | D45: =(D18/1.055*0.055)+(D21/1.055*0.055*0.75) -> 286.26483 | E45: =(E18/1.055*0.055)+(E21/1.055*0.055*0.75) -> 299.89649 | F45: =(F18/1.055*0.055)+(F21/1.055*0.055*0.75) -> 299.89649 | G45: =(G18/1.055*0.055)+(G21/1.055*0.055*0.75) -> 286.26483 | H45: =(H18/1.055*0.055)+(H21/1.055*0.055*0.75) -> 313.52815 | I45: =(I18/1.055*0.055)+(I21/1.055*0.055*0.75) -> 286.26483 | ... M45: =(M18/1.055*0.055)+(M21/1.055*0.055*0.75) -> 313.52815 | O45: =SUM(B45:M45) -> 3557.8629
A46: Report Crédit de TVA M-1 | C46: =IF(B47<0,B47,"") -> -7396.7185 | D46: =IF(C47<0,C47,"") -> -6486.691 | E46: =IF(D47<0,D47,"") -> -5528.9122 | F46: =IF(E47<0,E47,"") -> -4606.7154 | G46: =IF(F47<0,F47,"") -> -3684.5185 | H46: =IF(G47<0,G47,"") -> -2726.7397 | I46: =IF(H47<0,H47,"") -> -1715.1249 | J46: =IF(I47<0,I47,"") -> -757.34606 | ... M46: =IF(L47<0,L47,"") | O46: =SUM(B46:M46) -> -32902.766
A47: Solde de TVA mensuel | B47: =(SUM(B40:B42))-(SUM(B43:B46)) -> -7396.7185 | C47: =(SUM(C40:C42))-(SUM(C43:C45))+C46 -> -6486.691 | D47: =(SUM(D40:D42))-(SUM(D43:D45))+D46 -> -5528.9122 | E47: =(SUM(E40:E42))-(SUM(E43:E45))+E46 -> -4606.7154 | F47: =(SUM(F40:F42))-(SUM(F43:F45))+F46 -> -3684.5185 | G47: =(SUM(G40:G42))-(SUM(G43:G45))+G46 -> -2726.7397 | H47: =(SUM(H40:H42))-(SUM(H43:H45))+H46 -> -1715.1249 | I47: =(SUM(I40:I42))-(SUM(I43:I45))+I46 -> -757.34606 | J47: =(SUM(J40:J42))-(SUM(J43:J45))+J46 -> 164.85078 | K47: =(SUM(K40:K42))-(SUM(K43:K45)) -> 1011.6149 | L47: =(SUM(L40:L42))-(SUM(L43:L45)) -> 910.02743 | M47: =(SUM(M40:M42))-(SUM(M43:M45)) -> 1053.2815 | O47: =SUM(B47:M47) -> -29762.992
A48: TVA A DECAISSER | C48: =IF(B47>0,B47,0) -> 0 | D48: =IF(C47>0,C47,0) -> 0 | E48: =IF(D47>0,D47,0) -> 0 | F48: =IF(E47>0,E47,0) -> 0 | G48: =IF(F47>0,F47,0) -> 0 | H48: =IF(G47>0,G47,0) -> 0 | I48: =IF(H47>0,H47,0) -> 0 | J48: =IF(I47>0,I47,0) -> 0 | ... M48: =IF(L47>0,L47,0) -> 910.02743
A50: Solde du mois | B50: =B12-(B16+B38+B48) -> 10461.905 | C50: =C12-(C16+C38+C48) -> 1231.9054 | D50: =D12-(D16+D38+D48) -> 1541.9054 | E50: =E12-(E16+E38+E48) -> 1351.9054 | F50: =F12-(F16+F38+F48) -> 1351.9054 | G50: =G12-(G16+G38+G48) -> 1541.9054 | H50: =H12-(H16+H38+H48) -> 1911.9054 | I50: =I12-(I16+I38+I48) -> 1541.9054 | ... M50: =M12-(M16+M38+M48) -> 1251.878
A51: TRESORERIE CUMULEE FIN DE MOIS | B51: =B3+B50 -> 10461.905 | C51: =C3+C50 -> 11693.811 | D51: =D3+D50 -> 13235.716 | E51: =E3+E50 -> 14587.622 | F51: =F3+F50 -> 15939.527 | G51: =G3+G50 -> 17481.433 | H51: =H3+H50 -> 19393.338 | I51: =I3+I50 -> 20935.243 | ... M51: =M3+M50 -> 25506.372

Sheet Trésorerie année 2
A1: Budget de trésorerie | B1: =Paramètres!D3 -> 2026
A2: Régime fiscal EURL
A3: Trésorerie début de mois | B3: ='Trésorerie année 1'!M51 -> 25506.372 | C3: =B51 -> 26115.808 | D3: =C51 -> 27018.152 | E3: =D51 -> 28219.244 | F3: =E51 -> 29644.08 | G3: =F51 -> 30911.836 | H3: =G51 -> 32558.133 | I3: =H51 -> 34265.048 | J3: =I51 -> 34978.011 | ... M3: =L51 -> 39316.9
B5: Janvier | C5: Février | D5: Mars | E5: Avril | F5: Mai | G5: Juin | H5: Juillet | I5: Août | J5: Septembre | K5: Octobre | L5: Novembre | M5: Décembre | O5: TOTAL
A6: Nb de jours ouvrables | B6: =NETWORKDAYS(DATE(Paramètres!$D$3,COLUMN()-1,1),EOMONTH(DATE(Paramètres!$D$3,COLUMN()-1,1),0)) -> 22 | C6: =NETWORKDAYS(DATE(Paramètres!$D$3,COLUMN()-1,1),EOMONTH(DATE(Paramètres!$D$3,COLUMN()-1,1),0)) -> 20 | D6: =NETWORKDAYS(DATE(Paramètres!$D$3,COLUMN()-1,1),EOMONTH(DATE(Paramètres!$D$3,COLUMN()-1,1),0)) -> 22 | E6: =NETWORKDAYS(DATE(Paramètres!$D$3,COLUMN()-1,1),EOMONTH(DATE(Paramètres!$D$3,COLUMN()-1,1),0)) -> 22 | F6: =NETWORKDAYS(DATE(Paramètres!$D$3,COLUMN()-1,1),EOMONTH(DATE(Paramètres!$D$3,COLUMN()-1,1),0)) -> 21 | G6: =NETWORKDAYS(DATE(Paramètres!$D$3,COLUMN()-1,1),EOMONTH(DATE(Paramètres!$D$3,COLUMN()-1,1),0)) -> 22 | H6: =NETWORKDAYS(DATE(Paramètres!$D$3,COLUMN()-1,1),EOMONTH(DATE(Paramètres!$D$3,COLUMN()-1,1),0)) -> 23 | I6: =NETWORKDAYS(DATE(Paramètres!$D$3,COLUMN()-1,1),EOMONTH(DATE(Paramètres!$D$3,COLUMN()-1,1),0)) -> 21 | ... M6: =NETWORKDAYS(DATE(Paramètres!$D$3,COLUMN()-1,1),EOMONTH(DATE(Paramètres!$D$3,COLUMN()-1,1),0)) -> 23 | O6: =SUM(B6:M6) -> 261
A7: Ventes repas | B7: =(Paramètres!$D$8*Paramètres!$D$4*'Trésorerie année 2'!B6) -> 19057.5 | C7: =(Paramètres!$D$8*Paramètres!$D$4*'Trésorerie année 2'!C6) -> 17325 | D7: =(Paramètres!$D$8*Paramètres!$D$4*'Trésorerie année 2'!D6) -> 19057.5 | E7: =(Paramètres!$D$8*Paramètres!$D$4*'Trésorerie année 2'!E6) -> 19057.5 | F7: =(Paramètres!$D$8*Paramètres!$D$4*'Trésorerie année 2'!F6) -> 18191.25 | G7: =(Paramètres!$D$8*Paramètres!$D$4*'Trésorerie année 2'!G6) -> 19057.5 | H7: =(Paramètres!$D$8*Paramètres!$D$4*'Trésorerie année 2'!H6) -> 19923.75 | I7: =(Paramètres!$D$8*Paramètres!$D$4*'Trésorerie année 2'!I6) -> 18191.25 | ... M7: =(Paramètres!$D$8*Paramètres!$D$4*'Trésorerie année 2'!M6) -> 19923.75 | O7: =SUM(B7:M7) -> 226091.25
A8: Ventes Boissons | B8: =Paramètres!$D$8*'Trésorerie année 2'!B6*Paramètres!$D$6*3 -> 907.5 | C8: =Paramètres!$D$8*'Trésorerie année 2'!C6*Paramètres!$D$6*3 -> 825 | D8: =Paramètres!$D$8*'Trésorerie année 2'!D6*Paramètres!$D$6*3 -> 907.5 | E8: =Paramètres!$D$8*'Trésorerie année 2'!E6*Paramètres!$D$6*3 -> 907.5 | F8: =Paramètres!$D$8*'Trésorerie année 2'!F6*Paramètres!$D$6*3 -> 866.25 | G8: =Paramètres!$D$8*'Trésorerie année 2'!G6*Paramètres!$D$6*3 -> 907.5 | H8: =Paramètres!$D$8*'Trésorerie année 2'!H6*Paramètres!$D$6*3 -> 948.75 | I8: =Paramètres!$D$8*'Trésorerie année 2'!I6*Paramètres!$D$6*3 -> 866.25 | ... M8: =Paramètres!$D$8*'Trésorerie année 2'!M6*Paramètres!$D$6*3 -> 948.75 | O8: =SUM(B8:M8) -> 10766.25
A9: Apport personnel - associés | B9: 0 | O9: =SUM(B9:M9) -> 0
A10: Prêts et financements | B10: 0 | O10: =SUM(B10:M10) -> 0
A11: Aides & Subventions | B11: ='Plan de financement initial'!H16+'Plan de financement initial'!H19+'Plan de financement initial'!H24 -> 0 | O11: =SUM(B11:M11) -> 0
A12: ENCAISSEMENTS | B12: =SUM(B7:B11) -> 19965 | C12: =SUM(C7:C11) -> 18150 | D12: =SUM(D7:D11) -> 19965 | E12: =SUM(E7:E11) -> 19965 | F12: =SUM(F7:F11) -> 19057.5 | G12: =SUM(G7:G11) -> 19965 | H12: =SUM(H7:H11) -> 20872.5 | I12: =SUM(I7:I11) -> 19057.5 | ... M12: =SUM(M7:M11) -> 20872.5 | O12: =SUM(B12:M12) -> 236857.5 | P12: =IF(O12=SUM(O7:O11),"ok","non") -> ok
A14: Immobilisations incorporelles | B14: 0 | C14: 0 | D14: 0 | E14: 0 | F14: 0 | G14: 0 | H14: 0 | I14: 0 | J14: 0 | K14: 0 | L14: 0 | M14: 0 | O14: =SUM(B14:M14) -> 0
A15: Immobilisations corporelles | B15: 0 | C15: =IF(C5=Paramètres!$C$14,Paramètres!$C$13,0) -> 0 | D15: =IF(D5=Paramètres!$C$14,Paramètres!$C$13,0) -> 0 | E15: =IF(E5=Paramètres!$C$14,Paramètres!$C$13,0) -> 0 | F15: 0 | G15: =IF(G5=Paramètres!$C$14,Paramètres!$C$13,0) -> 0 | H15: =IF(H5=Paramètres!$C$14,Paramètres!$C$13,0) -> 0 | I15: =IF(I5=Paramètres!$C$14,Paramètres!$C$13,0) -> 0 | J15: =IF(J5=Paramètres!$C$14,Paramètres!$C$13,0) -> 0 | K15: =IF(K5=Paramètres!$C$14,Paramètres!$C$13,0) -> 0 | L15: =IF(L5=Paramètres!$C$14,Paramètres!$C$13,0) -> 0 | M15: =IF(M5=Paramètres!$C$14,Paramètres!$C$13,0) -> 0 | O15: =SUM(B15:M15) -> 0
A16: IMMOBILISATIONS | B16: =SUM(B14:B15) -> 0 | C16: =SUM(C14:C15) -> 0 | D16: =SUM(D14:D15) -> 0 | E16: =SUM(E14:E15) -> 0 | F16: =SUM(F14:F15) -> 0 | G16: =SUM(G14:G15) -> 0 | H16: =SUM(H14:H15) -> 0 | I16: =SUM(I14:I15) -> 0 | ... M16: =SUM(M14:M15) -> 0 | O16: =SUM(B16:M16) -> 0 | P16: =IF(O16=SUM(O14:O15),"ok","non") -> ok
A18: Achats de MP | B18: =B7*Paramètres!$D$5 -> 6670.125 | C18: =C7*Paramètres!$D$5 -> 6063.75 | D18: =D7*Paramètres!$D$5 -> 6670.125 | E18: =E7*Paramètres!$D$5 -> 6670.125 | F18: =F7*Paramètres!$D$5 -> 6366.9375 | G18: =G7*Paramètres!$D$5 -> 6670.125 | H18: =H7*Paramètres!$D$5 -> 6973.3125 | I18: =I7*Paramètres!$D$5 -> 6366.9375 | ... M18: =M7*Paramètres!$D$5 -> 6973.3125 | O18: =SUM(B18:M18) -> 79131.938
A19: Emballages | B19: =Paramètres!$D$7*Paramètres!$D$8*'Trésorerie année 2'!B6 -> 326.7 | C19: =Paramètres!$D$7*Paramètres!$D$8*'Trésorerie année 2'!C6 -> 297 | D19: =Paramètres!$D$7*Paramètres!$D$8*'Trésorerie année 2'!D6 -> 326.7 | E19: =Paramètres!$D$7*Paramètres!$D$8*'Trésorerie année 2'!E6 -> 326.7 | F19: =Paramètres!$D$7*Paramètres!$D$8*'Trésorerie année 2'!F6 -> 311.85 | G19: =Paramètres!$D$7*Paramètres!$D$8*'Trésorerie année 2'!G6 -> 326.7 | H19: =Paramètres!$D$7*Paramètres!$D$8*'Trésorerie année 2'!H6 -> 341.55 | I19: =Paramètres!$D$7*Paramètres!$D$8*'Trésorerie année 2'!I6 -> 311.85 | ... M19: =Paramètres!$D$7*Paramètres!$D$8*'Trésorerie année 2'!M6 -> 341.55 | O19: =SUM(B19:M19) -> 3875.85
A20: Carburant | B20: =Paramètres!$D$9*Paramètres!$D$12*'Trésorerie année 2'!B6 -> 84.7 | C20: =Paramètres!$D$9*Paramètres!$D$12*'Trésorerie année 2'!C6 -> 77 | D20: =Paramètres!$D$9*Paramètres!$D$12*'Trésorerie année 2'!D6 -> 84.7 | E20: =Paramètres!$D$9*Paramètres!$D$12*'Trésorerie année 2'!E6 -> 84.7 | F20: =Paramètres!$D$9*Paramètres!$D$12*'Trésorerie année 2'!F6 -> 80.85 | G20: =Paramètres!$D$9*Paramètres!$D$12*'Trésorerie année 2'!G6 -> 84.7 | H20: =Paramètres!$D$9*Paramètres!$D$12*'Trésorerie année 2'!H6 -> 88.55 | I20: =Paramètres!$D$9*Paramètres!$D$12*'Trésorerie année 2'!I6 -> 80.85 | ... M20: =Paramètres!$D$9*Paramètres!$D$12*'Trésorerie année 2'!M6 -> 88.55 | O20: =SUM(B20:M20) -> 1004.85
A21: Achats marchandises (boissons) | B21: =B8*Paramètres!$D$6 -> 226.875 | C21: =C8*Paramètres!$D$6 -> 206.25 | D21: =D8*Paramètres!$D$6 -> 226.875 | E21: =E8*Paramètres!$D$6 -> 226.875 | F21: =F8*Paramètres!$D$6 -> 216.5625 | G21: =G8*Paramètres!$D$6 -> 226.875 | H21: =H8*Paramètres!$D$6 -> 237.1875 | I21: =I8*Paramètres!$D$6 -> 216.5625 | ... M21: =M8*Paramètres!$D$6 -> 237.1875 | O21: =SUM(B21:M21) -> 2691.5625
A22: Fluides (eau, électricité, gaz, etc.) | B22: =B7*0.05 -> 952.875 | C22: =C7*0.05 -> 866.25 | D22: =D7*0.05 -> 952.875 | E22: =E7*0.05 -> 952.875 | F22: =F7*0.05 -> 909.5625 | G22: =G7*0.05 -> 952.875 | H22: =H7*0.05 -> 996.1875 | I22: =I7*0.05 -> 909.5625 | ... M22: =M7*0.05 -> 996.1875 | O22: =SUM(B22:M22) -> 11304.563
A23: Frais d'emplacement (AOT) | B23: =Paramètres!$D$10*'Trésorerie année 2'!B6 -> 3465 | C23: =Paramètres!$D$10*'Trésorerie année 2'!C6 -> 3150 | D23: =Paramètres!$D$10*'Trésorerie année 2'!D6 -> 3465 | E23: =Paramètres!$D$10*'Trésorerie année 2'!E6 -> 3465 | F23: =Paramètres!$D$10*'Trésorerie année 2'!F6 -> 3307.5 | G23: =Paramètres!$D$10*'Trésorerie année 2'!G6 -> 3465 | H23: =Paramètres!$D$10*'Trésorerie année 2'!H6 -> 3622.5 | I23: =Paramètres!$D$10*'Trésorerie année 2'!I6 -> 3307.5 | ... M23: =Paramètres!$D$10*'Trésorerie année 2'!M6 -> 3622.5 | O23: =SUM(B23:M23) -> 41107.5
A24: Loyer local labo | B24: 500 | C24: 500 | D24: 500 | E24: 500 | F24: 500 | G24: 500 | H24: 500 | I24: 500 | J24: 500 | K24: 500 | L24: 500 | M24: 500 | O24: =SUM(B24:M24) -> 6000
A25: Frais internet-téléphone | B25: =20 -> 20 | C25: 20 | D25: 20 | E25: 20 | F25: 20 | G25: 20 | H25: 20 | I25: 20 | J25: 20 | K25: 20 | L25: 20 | M25: 20 | O25: =SUM(B25:M25) -> 240
A26: Frais logiciel TPE | B26: =(B7+B8)*0.01 -> 199.65 | C26: =(C7+C8)*0.01 -> 181.5 | D26: =(D7+D8)*0.01 -> 199.65 | E26: =(E7+E8)*0.01 -> 199.65 | F26: =(F7+F8)*0.01 -> 190.575 | G26: =(G7+G8)*0.01 -> 199.65 | H26: =(H7+H8)*0.01 -> 208.725 | I26: =(I7+I8)*0.01 -> 190.575 | ... M26: =(M7+M8)*0.01 -> 208.725 | O26: =SUM(B26:M26) -> 2368.575
A27: Fournitures diverses | B27: 250 | E27: 250 | H27: 250 | K27: 250 | O27: =SUM(B27:M27) -> 1000
A28: Entretien / Maintenance | B28: 150 | C28: 150 | D28: 150 | E28: 150 | F28: 150 | G28: 150 | H28: 150 | I28: 150 | J28: 150 | K28: 150 | L28: 150 | M28: 150 | O28: =SUM(B28:M28) -> 1800
A29: Assurances (camion, local, RC) | B29: 225 | C29: 225 | D29: 225 | E29: 225 | F29: 225 | G29: 225 | H29: 225 | I29: 225 | J29: 225 | K29: 225 | L29: 225 | M29: 225 | O29: =SUM(B29:M29) -> 2700
A30: Publicité / Communication / Mkgt | D30: 500 | I30: 500 | O30: =SUM(B30:M30) -> 1000
A31: Honoraires (prestataires divers) | B31: =100 -> 100 | C31: 100 | D31: 100 | E31: 100 | F31: 100 | G31: 100 | H31: 100 | I31: 100 | J31: 100 | K31: 100 | L31: 100 | M31: 100 | O31: =SUM(B31:M31) -> 1200
A32: Mutuelle | B32: 100 | C32: 100 | D32: 100 | E32: 100 | F32: 100 | G32: 100 | H32: 100 | I32: 100 | J32: 100 | K32: 100 | L32: 100 | M32: 100 | O32: =SUM(B32:M32) -> 1200
A33: Salaires Bruts Gérant | B33: ='Trésorerie année 1'!B33*1.1 -> 2420 | C33: ='Trésorerie année 1'!C33*1.1 -> 2420 | D33: ='Trésorerie année 1'!D33*1.1 -> 2420 | E33: ='Trésorerie année 1'!E33*1.1 -> 2420 | F33: ='Trésorerie année 1'!F33*1.1 -> 2420 | G33: ='Trésorerie année 1'!G33*1.1 -> 2420 | H33: ='Trésorerie année 1'!H33*1.1 -> 2420 | I33: ='Trésorerie année 1'!I33*1.1 -> 2420 | ... M33: ='Trésorerie année 1'!M33*1.1 -> 2420 | O33: =SUM(B33:M33) -> 29040
A34: Charges sociales patronales Gérant | B34: =B33*0.45 -> 1089 | C34: =C33*0.45 -> 1089 | D34: =D33*0.45 -> 1089 | E34: =E33*0.45 -> 1089 | F34: =F33*0.45 -> 1089 | G34: =G33*0.45 -> 1089 | H34: =H33*0.45 -> 1089 | I34: =I33*0.45 -> 1089 | ... M34: =M33*0.45 -> 1089 | O34: =SUM(B34:M34) -> 13068
A35: Frais financiers (frais TC, î) | B35: 10 | C35: 10 | D35: 10 | E35: 10 | F35: 10 | G35: 10 | H35: 10 | I35: 10 | J35: 10 | K35: 10 | L35: 10 | M35: 10 | O35: =SUM(B35:M35) -> 120
A36: Échéances d'emprunt | B36: =IF(Paramètres!$C$15="",0,-PMT(Paramètres!$C$16/12,Paramètres!$C$17*12,Paramètres!$C$15)) -> 673.09456 | C36: =IF(Paramètres!$C$15="",0,-PMT(Paramètres!$C$16/12,Paramètres!$C$17*12,Paramètres!$C$15)) -> 673.09456 | D36: =IF(Paramètres!$C$15="",0,-PMT(Paramètres!$C$16/12,Paramètres!$C$17*12,Paramètres!$C$15)) -> 673.09456 | E36: =IF(Paramètres!$C$15="",0,-PMT(Paramètres!$C$16/12,Paramètres!$C$17*12,Paramètres!$C$15)) -> 673.09456 | F36: =IF(Paramètres!$C$15="",0,-PMT(Paramètres!$C$16/12,Paramètres!$C$17*12,Paramètres!$C$15)) -> 673.09456 | G36: =IF(Paramètres!$C$15="",0,-PMT(Paramètres!$C$16/12,Paramètres!$C$17*12,Paramètres!$C$15)) -> 673.09456 | H36: =IF(Paramètres!$C$15="",0,-PMT(Paramètres!$C$16/12,Paramètres!$C$17*12,Paramètres!$C$15)) -> 673.09456 | I36: =IF(Paramètres!$C$15="",0,-PMT(Paramètres!$C$16/12,Paramètres!$C$17*12,Paramètres!$C$15)) -> 673.09456 | ... M36: =IF(Paramètres!$C$15="",0,-PMT(Paramètres!$C$16/12,Paramètres!$C$17*12,Paramètres!$C$15)) -> 673.09456 | O36: =SUM(B36:M36) -> 8077.1348
A37: IS ou autres selon régime jurid | B37: ='CR pluriannuel '!D11 -> 839.26302 | O37: =SUM(B37:M37) -> 839.26302
A38: DECAISSEMENTS | B38: =SUM(B18:B37) -> 18302.283 | C38: =SUM(C18:C37) -> 16128.845 | D38: =SUM(D18:D37) -> 17713.02 | E38: =SUM(E18:E37) -> 17463.02 | F38: =SUM(F18:F37) -> 16670.932 | G38: =SUM(G18:G37) -> 17213.02 | H38: =SUM(H18:H37) -> 18005.107 | I38: =SUM(I18:I37) -> 17170.932 | ... M38: =SUM(M18:M37) -> 17755.107 | O38: =SUM(B38:M38) -> 207769.24 | P38: =IF(O38=SUM(O18:O37),"ok","non") -> ok
A40: TVA collectée 20% | B40: =B8/1.2*0.2*0.25 -> 37.8125 | C40: =C8/1.2*0.2*0.25 -> 34.375 | D40: =D8/1.2*0.2*0.25 -> 37.8125 | E40: =E8/1.2*0.2*0.25 -> 37.8125 | F40: =F8/1.2*0.2*0.25 -> 36.09375 | G40: =G8/1.2*0.2*0.25 -> 37.8125 | H40: =H8/1.2*0.2*0.25 -> 39.53125 | I40: =I8/1.2*0.2*0.25 -> 36.09375 | ... M40: =M8/1.2*0.2*0.25 -> 39.53125 | O40: =SUM(B40:M40) -> 448.59375
A41: TVA Collectée 10% | B41: =B7/1.1*0.1+B8/1.1*0.1*0.75 -> 1794.375 | C41: =C7/1.1*0.1+C8/1.1*0.1*0.75 -> 1631.25 | D41: =D7/1.1*0.1+D8/1.1*0.1*0.75 -> 1794.375 | E41: =E7/1.1*0.1+E8/1.1*0.1*0.75 -> 1794.375 | F41: =F7/1.1*0.1+F8/1.1*0.1*0.75 -> 1712.8125 | G41: =G7/1.1*0.1+G8/1.1*0.1*0.75 -> 1794.375 | H41: =H7/1.1*0.1+H8/1.1*0.1*0.75 -> 1875.9375 | I41: =I7/1.1*0.1+I8/1.1*0.1*0.75 -> 1712.8125 | ... M41: =M7/1.1*0.1+M8/1.1*0.1*0.75 -> 1875.9375 | O41: =SUM(B41:M41) -> 21287.813
A42: TVA collectée 5,5% | O42: =SUM(B42:M42) -> 0
A43: TVA déductible 20% | B43: =(B16/1.2*0.2)+(B19/1.2*0.2)+(B20/1.2*0.2)+(B21/1.2*0.2*0.25)+(B22/1.2*0.2)+(B25/1.2*0.2)+(B26/1.2*0.2)+(B27/1.2*0.2)+(B28/1.2*0.2)+(B30/1.2*0.2)+(B31/1.2*0.2) -> 356.77396 | C43: =(C16/1.2*0.2)+(C19/1.2*0.2)+(C20/1.2*0.2)+(C21/1.2*0.2*0.25)+(C22/1.2*0.2)+(C25/1.2*0.2)+(C26/1.2*0.2)+(C27/1.2*0.2)+(C28/1.2*0.2)+(C30/1.2*0.2)+(C31/1.2*0.2) -> 290.55208 | D43: =(D16/1.2*0.2)+(D19/1.2*0.2)+(D20/1.2*0.2)+(D21/1.2*0.2*0.25)+(D22/1.2*0.2)+(D25/1.2*0.2)+(D26/1.2*0.2)+(D27/1.2*0.2)+(D28/1.2*0.2)+(D30/1.2*0.2)+(D31/1.2*0.2) -> 398.44063 | E43: =(E16/1.2*0.2)+(E19/1.2*0.2)+(E20/1.2*0.2)+(E21/1.2*0.2*0.25)+(E22/1.2*0.2)+(E25/1.2*0.2)+(E26/1.2*0.2)+(E27/1.2*0.2)+(E28/1.2*0.2)+(E30/1.2*0.2)+(E31/1.2*0.2) -> 356.77396 | F43: =(F16/1.2*0.2)+(F19/1.2*0.2)+(F20/1.2*0.2)+(F21/1.2*0.2*0.25)+(F22/1.2*0.2)+(F25/1.2*0.2)+(F26/1.2*0.2)+(F27/1.2*0.2)+(F28/1.2*0.2)+(F30/1.2*0.2)+(F31/1.2*0.2) -> 302.82969 | G43: =(G16/1.2*0.2)+(G19/1.2*0.2)+(G20/1.2*0.2)+(G21/1.2*0.2*0.25)+(G22/1.2*0.2)+(G25/1.2*0.2)+(G26/1.2*0.2)+(G27/1.2*0.2)+(G28/1.2*0.2)+(G30/1.2*0.2)+(G31/1.2*0.2) -> 315.10729 | H43: =(H16/1.2*0.2)+(H19/1.2*0.2)+(H20/1.2*0.2)+(H21/1.2*0.2*0.25)+(H22/1.2*0.2)+(H25/1.2*0.2)+(H26/1.2*0.2)+(H27/1.2*0.2)+(H28/1.2*0.2)+(H30/1.2*0.2)+(H31/1.2*0.2) -> 369.05156 | I43: =(I16/1.2*0.2)+(I19/1.2*0.2)+(I20/1.2*0.2)+(I21/1.2*0.2*0.25)+(I22/1.2*0.2)+(I25/1.2*0.2)+(I26/1.2*0.2)+(I27/1.2*0.2)+(I28/1.2*0.2)+(I30/1.2*0.2)+(I31/1.2*0.2) -> 386.16302 | ... M43: =(M16/1.2*0.2)+(M19/1.2*0.2)+(M20/1.2*0.2)+(M21/1.2*0.2*0.25)+(M22/1.2*0.2)+(M25/1.2*0.2)+(M26/1.2*0.2)+(M27/1.2*0.2)+(M28/1.2*0.2)+(M30/1.2*0.2)+(M31/1.2*0.2) -> 327.3849 | O43: =SUM(B43:M43) -> 4077.788
A44: TVA Déductible 10% | O44: =SUM(B44:M44) -> 0
A45: TVA Déductible 5,5% | B45: =(B18/1.055*0.055)+(B21/1.055*0.055*0.75) -> 356.60234 | C45: =(C18/1.055*0.055)+(C21/1.055*0.055*0.75) -> 324.18395 | D45: =(D18/1.055*0.055)+(D21/1.055*0.055*0.75) -> 356.60234 | E45: =(E18/1.055*0.055)+(E21/1.055*0.055*0.75) -> 356.60234 | F45: =(F18/1.055*0.055)+(F21/1.055*0.055*0.75) -> 340.39314 | G45: =(G18/1.055*0.055)+(G21/1.055*0.055*0.75) -> 356.60234 | H45: =(H18/1.055*0.055)+(H21/1.055*0.055*0.75) -> 372.81154 | I45: =(I18/1.055*0.055)+(I21/1.055*0.055*0.75) -> 340.39314 | ... M45: =(M18/1.055*0.055)+(M21/1.055*0.055*0.75) -> 372.81154 | O45: =SUM(B45:M45) -> 4230.6005
A46: Report Crédit de TVA M-1 | C46: =IF(B47<0,B47,"") | D46: =IF(C47<0,C47,"") | E46: =IF(D47<0,D47,"") | F46: =IF(E47<0,E47,"") | G46: =IF(F47<0,F47,"") | H46: =IF(G47<0,G47,"") | I46: =IF(H47<0,H47,"") | J46: =IF(I47<0,I47,"") | ... M46: =IF(L47<0,L47,"") | O46: =SUM(B46:M46) -> 0
A47: Solde de TVA mensuel | B47: =(SUM(B40:B42))-(SUM(B43:B46)) -> 1118.8112 | C47: =(SUM(C40:C42))-(SUM(C43:C46)) -> 1050.889 | D47: =(SUM(D40:D42))-(SUM(D43:D46)) -> 1077.1445 | E47: =(SUM(E40:E42))-(SUM(E43:E46)) -> 1118.8112 | F47: =(SUM(F40:F42))-(SUM(F43:F46)) -> 1105.6834 | G47: =(SUM(G40:G42))-(SUM(G43:G46)) -> 1160.4779 | H47: =(SUM(H40:H42))-(SUM(H43:H46)) -> 1173.6057 | I47: =(SUM(I40:I42))-(SUM(I43:I46)) -> 1022.3501 | ... M47: =(SUM(M40:M42))-(SUM(M43:M46)) -> 1215.2723 | O47: =SUM(B47:M47) -> 13428.018
A48: TVA A DECAISSER | B48: ='Trésorerie année 1'!M47 -> 1053.2815 | C48: =IF(B47>0,B47,0) -> 1118.8112 | D48: =IF(C47>0,C47,0) -> 1050.889 | E48: =IF(D47>0,D47,0) -> 1077.1445 | F48: =IF(E47>0,E47,0) -> 1118.8112 | G48: =IF(F47>0,F47,0) -> 1105.6834 | H48: =IF(G47>0,G47,0) -> 1160.4779 | I48: =IF(H47>0,H47,0) -> 1173.6057 | J48: =IF(I47>0,I47,0) -> 1022.3501 | ... M48: =IF(L47>0,L47,0) -> 1105.6834
A50: Solde du mois | B50: =B12-(B16+B38+B48) -> 609.43587 | C50: =C12-(C16+C38+C48) -> 902.34423 | D50: =D12-(D16+D38+D48) -> 1201.0915 | E50: =E12-(E16+E38+E48) -> 1424.8359 | F50: =F12-(F16+F38+F48) -> 1267.7567 | G50: =G12-(G16+G38+G48) -> 1646.297 | H50: =H12-(H16+H38+H48) -> 1706.9151 | I50: =I12-(I16+I38+I48) -> 712.96229 | ... M50: =M12-(M16+M38+M48) -> 2011.7095
A51: TRESORERIE CUMULEE FIN DE MOIS | B51: =B3+B50 -> 26115.808 | C51: =C3+C50 -> 27018.152 | D51: =D3+D50 -> 28219.244 | E51: =E3+E50 -> 29644.08 | F51: =F3+F50 -> 30911.836 | G51: =G3+G50 -> 32558.133 | H51: =H3+H50 -> 34265.048 | I51: =I3+I50 -> 34978.011 | ... M51: =M3+M50 -> 41328.61

Sheet Trésorerie année 3
A1: Budget de trésorerie | B1: =Paramètres!$E$3 -> 2027
A2: Régime fiscal EURL
A3: Trésorerie début de mois | B3: ='Trésorerie année 2'!M51 -> 41328.61 | C3: =B51 -> 40626.03 | D3: =C51 -> 41405.743 | E3: =D51 -> 43416.904 | F3: =E51 -> 45063.218 | G3: =F51 -> 46634.565 | H3: =G51 -> 48617.485 | I3: =H51 -> 50340.436 | J3: =I51 -> 51796.72 | ... M3: =L51 -> 57223.938
B5: Janvier | C5: Février | D5: Mars | E5: Avril | F5: Mai | G5: Juin | H5: Juillet | I5: Août | J5: Septembre | K5: Octobre | L5: Novembre | M5: Décembre | O5: TOTAL
A6: Nb de jours ouvrables | B6: =NETWORKDAYS(DATE(Paramètres!$E$3,COLUMN()-1,1),EOMONTH(DATE(Paramètres!$E$3,COLUMN()-1,1),0)) -> 21 | C6: =NETWORKDAYS(DATE(Paramètres!$E$3,COLUMN()-1,1),EOMONTH(DATE(Paramètres!$E$3,COLUMN()-1,1),0)) -> 20 | D6: =NETWORKDAYS(DATE(Paramètres!$E$3,COLUMN()-1,1),EOMONTH(DATE(Paramètres!$E$3,COLUMN()-1,1),0)) -> 23 | E6: =NETWORKDAYS(DATE(Paramètres!$E$3,COLUMN()-1,1),EOMONTH(DATE(Paramètres!$E$3,COLUMN()-1,1),0)) -> 22 | F6: =NETWORKDAYS(DATE(Paramètres!$E$3,COLUMN()-1,1),EOMONTH(DATE(Paramètres!$E$3,COLUMN()-1,1),0)) -> 21 | G6: =NETWORKDAYS(DATE(Paramètres!$E$3,COLUMN()-1,1),EOMONTH(DATE(Paramètres!$E$3,COLUMN()-1,1),0)) -> 22 | H6: =NETWORKDAYS(DATE(Paramètres!$E$3,COLUMN()-1,1),EOMONTH(DATE(Paramètres!$E$3,COLUMN()-1,1),0)) -> 22 | I6: =NETWORKDAYS(DATE(Paramètres!$E$3,COLUMN()-1,1),EOMONTH(DATE(Paramètres!$E$3,COLUMN()-1,1),0)) -> 22 | ... M6: =NETWORKDAYS(DATE(Paramètres!$E$3,COLUMN()-1,1),EOMONTH(DATE(Paramètres!$E$3,COLUMN()-1,1),0)) -> 23 | O6: =SUM(B6:M6) -> 261
A7: Ventes repas | B7: =(Paramètres!$E$8*Paramètres!$E$4*'Trésorerie année 3'!B6) -> 20055.853 | C7: =(Paramètres!$E$8*Paramètres!$E$4*'Trésorerie année 3'!C6) -> 19100.813 | D7: =(Paramètres!$E$8*Paramètres!$E$4*'Trésorerie année 3'!D6) -> 21965.934 | E7: =(Paramètres!$E$8*Paramètres!$E$4*'Trésorerie année 3'!E6) -> 21010.894 | F7: =(Paramètres!$E$8*Paramètres!$E$4*'Trésorerie année 3'!F6) -> 20055.853 | G7: =(Paramètres!$E$8*Paramètres!$E$4*'Trésorerie année 3'!G6) -> 21010.894 | H7: =(Paramètres!$E$8*Paramètres!$E$4*'Trésorerie année 3'!H6) -> 21010.894 | I7: =(Paramètres!$E$8*Paramètres!$E$4*'Trésorerie année 3'!I6) -> 21010.894 | ... M7: =(Paramètres!$E$8*Paramètres!$E$4*'Trésorerie année 3'!M6) -> 21965.934 | O7: =SUM(B7:M7) -> 249265.6
A8: Ventes Boissons | B8: =Paramètres!$E$8*'Trésorerie année 3'!B6*Paramètres!$E$6*3 -> 945.945 | C8: =Paramètres!$E$8*'Trésorerie année 3'!C6*Paramètres!$E$6*3 -> 900.9 | D8: =Paramètres!$E$8*'Trésorerie année 3'!D6*Paramètres!$E$6*3 -> 1036.035 | E8: =Paramètres!$E$8*'Trésorerie année 3'!E6*Paramètres!$E$6*3 -> 990.99 | F8: =Paramètres!$E$8*'Trésorerie année 3'!F6*Paramètres!$E$6*3 -> 945.945 | G8: =Paramètres!$E$8*'Trésorerie année 3'!G6*Paramètres!$E$6*3 -> 990.99 | H8: =Paramètres!$E$8*'Trésorerie année 3'!H6*Paramètres!$E$6*3 -> 990.99 | I8: =Paramètres!$E$8*'Trésorerie année 3'!I6*Paramètres!$E$6*3 -> 990.99 | ... M8: =Paramètres!$E$8*'Trésorerie année 3'!M6*Paramètres!$E$6*3 -> 1036.035 | O8: =SUM(B8:M8) -> 11756.745
A9: Apport personnel - associés | O9: =SUM(B9:M9) -> 0
A10: Prêts et financements | O10: =SUM(B10:M10) -> 0
A11: Aides & Subventions | B11: ='Plan de financement initial'!H16+'Plan de financement initial'!H19+'Plan de financement initial'!H24 -> 0 | O11: =SUM(B11:M11) -> 0
A12: ENCAISSEMENTS | B12: =SUM(B7:B11) -> 21001.798 | C12: =SUM(C7:C11) -> 20001.713 | D12: =SUM(D7:D11) -> 23001.969 | E12: =SUM(E7:E11) -> 22001.884 | F12: =SUM(F7:F11) -> 21001.798 | G12: =SUM(G7:G11) -> 22001.884 | H12: =SUM(H7:H11) -> 22001.884 | I12: =SUM(I7:I11) -> 22001.884 | ... M12: =SUM(M7:M11) -> 23001.969 | O12: =SUM(B12:M12) -> 261022.35 | P12: =IF(O12=SUM(O7:O11),"ok","non") -> ok
A14: Immobilisations incorporelles | B14: 0 | C14: 0 | D14: 0 | E14: 0 | F14: 0 | G14: 0 | H14: 0 | I14: 0 | J14: 0 | K14: 0 | L14: 0 | M14: 0 | O14: =SUM(B14:M14) -> 0
A15: Immobilisations corporelles | B15: 0 | C15: =IF(C5=Paramètres!$C$14,Paramètres!$C$13,0) -> 0 | D15: =IF(D5=Paramètres!$C$14,Paramètres!$C$13,0) -> 0 | E15: =IF(E5=Paramètres!$C$14,Paramètres!$C$13,0) -> 0 | F15: 0 | G15: =IF(G5=Paramètres!$C$14,Paramètres!$C$13,0) -> 0 | H15: =IF(H5=Paramètres!$C$14,Paramètres!$C$13,0) -> 0 | I15: =IF(I5=Paramètres!$C$14,Paramètres!$C$13,0) -> 0 | J15: =IF(J5=Paramètres!$C$14,Paramètres!$C$13,0) -> 0 | K15: =IF(K5=Paramètres!$C$14,Paramètres!$C$13,0) -> 0 | L15: =IF(L5=Paramètres!$C$14,Paramètres!$C$13,0) -> 0 | M15: =IF(M5=Paramètres!$C$14,Paramètres!$C$13,0) -> 0 | O15: =SUM(B15:M15) -> 0
A16: IMMOBILISATIONS | B16: =SUM(B14:B15) -> 0 | C16: =SUM(C14:C15) -> 0 | D16: =SUM(D14:D15) -> 0 | E16: =SUM(E14:E15) -> 0 | F16: =SUM(F14:F15) -> 0 | G16: =SUM(G14:G15) -> 0 | H16: =SUM(H14:H15) -> 0 | I16: =SUM(I14:I15) -> 0 | ... M16: =SUM(M14:M15) -> 0 | O16: =SUM(B16:M16) -> 0 | P16: =IF(O16=SUM(O14:O15),"ok","non") -> ok
A18: Achats de MP | B18: =B7*Paramètres!$E$5 -> 7220.1071 | C18: =C7*Paramètres!$E$5 -> 6876.2925 | D18: =D7*Paramètres!$E$5 -> 7907.7364 | E18: =E7*Paramètres!$E$5 -> 7563.9218 | F18: =F7*Paramètres!$E$5 -> 7220.1071 | G18: =G7*Paramètres!$E$5 -> 7563.9218 | H18: =H7*Paramètres!$E$5 -> 7563.9218 | I18: =I7*Paramètres!$E$5 -> 7563.9218 | ... M18: =M7*Paramètres!$E$5 -> 7907.7364 | O18: =SUM(B18:M18) -> 89735.617
A19: Emballages | B19: =Paramètres!$E$7*Paramètres!$E$8*'Trésorerie année 3'!B6 -> 327.4425 | C19: =Paramètres!$E$7*Paramètres!$E$8*'Trésorerie année 3'!C6 -> 311.85 | D19: =Paramètres!$E$7*Paramètres!$E$8*'Trésorerie année 3'!D6 -> 358.6275 | E19: =Paramètres!$E$7*Paramètres!$E$8*'Trésorerie année 3'!E6 -> 343.035 | F19: =Paramètres!$E$7*Paramètres!$E$8*'Trésorerie année 3'!F6 -> 327.4425 | G19: =Paramètres!$E$7*Paramètres!$E$8*'Trésorerie année 3'!G6 -> 343.035 | H19: =Paramètres!$E$7*Paramètres!$E$8*'Trésorerie année 3'!H6 -> 343.035 | I19: =Paramètres!$E$7*Paramètres!$E$8*'Trésorerie année 3'!I6 -> 343.035 | ... M19: =Paramètres!$E$7*Paramètres!$E$8*'Trésorerie année 3'!M6 -> 358.6275 | O19: =SUM(B19:M19) -> 4069.6425
A20: Carburant | B20: =Paramètres!$E$9*Paramètres!$E$12*'Trésorerie année 3'!B6 -> 88.935 | C20: =Paramètres!$E$9*Paramètres!$E$12*'Trésorerie année 3'!C6 -> 84.7 | D20: =Paramètres!$E$9*Paramètres!$E$12*'Trésorerie année 3'!D6 -> 97.405 | E20: =Paramètres!$E$9*Paramètres!$E$12*'Trésorerie année 3'!E6 -> 93.17 | F20: =Paramètres!$E$9*Paramètres!$E$12*'Trésorerie année 3'!F6 -> 88.935 | G20: =Paramètres!$E$9*Paramètres!$E$12*'Trésorerie année 3'!G6 -> 93.17 | H20: =Paramètres!$E$9*Paramètres!$E$12*'Trésorerie année 3'!H6 -> 93.17 | I20: =Paramètres!$E$9*Paramètres!$E$12*'Trésorerie année 3'!I6 -> 93.17 | ... M20: =Paramètres!$E$9*Paramètres!$E$12*'Trésorerie année 3'!M6 -> 97.405 | O20: =SUM(B20:M20) -> 1105.335
A21: Achats marchandises (boissons) | B21: =B8*Paramètres!$E$6 -> 245.9457 | C21: =C8*Paramètres!$E$6 -> 234.234 | D21: =D8*Paramètres!$E$6 -> 269.3691 | E21: =E8*Paramètres!$E$6 -> 257.6574 | F21: =F8*Paramètres!$E$6 -> 245.9457 | G21: =G8*Paramètres!$E$6 -> 257.6574 | H21: =H8*Paramètres!$E$6 -> 257.6574 | I21: =I8*Paramètres!$E$6 -> 257.6574 | ... M21: =M8*Paramètres!$E$6 -> 269.3691 | O21: =SUM(B21:M21) -> 3056.7537
A22: Fluides (eau, électricité, gaz, etc.) | B22: =B7*0.05 -> 1002.7927 | C22: =C7*0.05 -> 955.04063 | D22: =D7*0.05 -> 1098.2967 | E22: =E7*0.05 -> 1050.5447 | F22: =F7*0.05 -> 1002.7927 | G22: =G7*0.05 -> 1050.5447 | H22: =H7*0.05 -> 1050.5447 | I22: =I7*0.05 -> 1050.5447 | ... M22: =M7*0.05 -> 1098.2967 | O22: =SUM(B22:M22) -> 12463.28
A23: Frais d'emplacement (AOT) | B23: =Paramètres!$E$10*'Trésorerie année 3'!B6 -> 3472.875 | C23: =Paramètres!$E$10*'Trésorerie année 3'!C6 -> 3307.5 | D23: =Paramètres!$E$10*'Trésorerie année 3'!D6 -> 3803.625 | E23: =Paramètres!$E$10*'Trésorerie année 3'!E6 -> 3638.25 | F23: =Paramètres!$E$10*'Trésorerie année 3'!F6 -> 3472.875 | G23: =Paramètres!$E$10*'Trésorerie année 3'!G6 -> 3638.25 | H23: =Paramètres!$E$10*'Trésorerie année 3'!H6 -> 3638.25 | I23: =Paramètres!$E$10*'Trésorerie année 3'!I6 -> 3638.25 | ... M23: =Paramètres!$E$10*'Trésorerie année 3'!M6 -> 3803.625 | O23: =SUM(B23:M23) -> 43162.875
A24: Loyer local labo | B24: 500 | C24: 500 | D24: 500 | E24: 500 | F24: 500 | G24: 500 | H24: 500 | I24: 500 | J24: 500 | K24: 500 | L24: 500 | M24: 500 | O24: =SUM(B24:M24) -> 6000
A25: Frais internet-téléphone | B25: =20 -> 20 | C25: 20 | D25: 20 | E25: 20 | F25: 20 | G25: 20 | H25: 20 | I25: 20 | J25: 20 | K25: 20 | L25: 20 | M25: 20 | O25: =SUM(B25:M25) -> 240
A26: Frais logiciel TPE | B26: =(B7+B8)*0.01 -> 210.01798 | C26: =(C7+C8)*0.01 -> 200.01713 | D26: =(D7+D8)*0.01 -> 230.01969 | E26: =(E7+E8)*0.01 -> 220.01884 | F26: =(F7+F8)*0.01 -> 210.01798 | G26: =(G7+G8)*0.01 -> 220.01884 | H26: =(H7+H8)*0.01 -> 220.01884 | I26: =(I7+I8)*0.01 -> 220.01884 | ... M26: =(M7+M8)*0.01 -> 230.01969 | O26: =SUM(B26:M26) -> 2610.2235
A27: Fournitures diverses | C27: 400 | E27: 300 | H27: 200 | K27: 100 | O27: =SUM(B27:M27) -> 1000
A28: Entretien / Maintenance | B28: 150 | C28: 150 | D28: 150 | E28: 150 | F28: 150 | G28: 150 | H28: 150 | I28: 150 | J28: 150 | K28: 150 | L28: 150 | M28: 150 | O28: =SUM(B28:M28) -> 1800
A29: Assurances (camion, local, RC) | B29: 225 | C29: 225 | D29: 225 | E29: 225 | F29: 225 | G29: 225 | H29: 225 | I29: 225 | J29: 225 | K29: 225 | L29: 225 | M29: 225 | O29: =SUM(B29:M29) -> 2700
A30: Publicité / Communication / Mkgt | D30: 500 | I30: 500 | O30: =SUM(B30:M30) -> 1000
A31: Honoraires (prestataires divers) | B31: =100 -> 100 | C31: 100 | D31: 100 | E31: 100 | F31: 100 | G31: 100 | H31: 100 | I31: 100 | J31: 100 | K31: 100 | L31: 100 | M31: 100 | O31: =SUM(B31:M31) -> 1200
A32: Mutuelle | B32: 100 | C32: 100 | D32: 100 | E32: 100 | F32: 100 | G32: 100 | H32: 100 | I32: 100 | J32: 100 | K32: 100 | L32: 100 | M32: 100 | O32: =SUM(B32:M32) -> 1200
A33: Salaires Bruts Gérant | B33: ='Trésorerie année 2'!B33*1.1 -> 2662 | C33: ='Trésorerie année 2'!C33*1.1 -> 2662 | D33: ='Trésorerie année 2'!D33*1.1 -> 2662 | E33: ='Trésorerie année 2'!E33*1.1 -> 2662 | F33: ='Trésorerie année 2'!F33*1.1 -> 2662 | G33: ='Trésorerie année 2'!G33*1.1 -> 2662 | H33: ='Trésorerie année 2'!H33*1.1 -> 2662 | I33: ='Trésorerie année 2'!I33*1.1 -> 2662 | ... M33: ='Trésorerie année 2'!M33*1.1 -> 2662 | O33: =SUM(B33:M33) -> 31944
A34: Charges sociales patronales Gérant | B34: =B33*0.45 -> 1197.9 | C34: =C33*0.45 -> 1197.9 | D34: =D33*0.45 -> 1197.9 | E34: =E33*0.45 -> 1197.9 | F34: =F33*0.45 -> 1197.9 | G34: =G33*0.45 -> 1197.9 | H34: =H33*0.45 -> 1197.9 | I34: =I33*0.45 -> 1197.9 | ... M34: =M33*0.45 -> 1197.9 | O34: =SUM(B34:M34) -> 14374.8
A35: Frais financiers (frais TC, î) | B35: 10 | C35: 10 | D35: 10 | E35: 10 | F35: 10 | G35: 10 | H35: 10 | I35: 10 | J35: 10 | K35: 10 | L35: 10 | M35: 10 | O35: =SUM(B35:M35) -> 120
A36: Échéances d'emprunt | B36: =IF(Paramètres!$C$15="",0,-PMT(Paramètres!$C$16/12,Paramètres!$C$17*12,Paramètres!$C$15)) -> 673.09456 | C36: =IF(Paramètres!$C$15="",0,-PMT(Paramètres!$C$16/12,Paramètres!$C$17*12,Paramètres!$C$15)) -> 673.09456 | D36: =IF(Paramètres!$C$15="",0,-PMT(Paramètres!$C$16/12,Paramètres!$C$17*12,Paramètres!$C$15)) -> 673.09456 | E36: =IF(Paramètres!$C$15="",0,-PMT(Paramètres!$C$16/12,Paramètres!$C$17*12,Paramètres!$C$15)) -> 673.09456 | F36: =IF(Paramètres!$C$15="",0,-PMT(Paramètres!$C$16/12,Paramètres!$C$17*12,Paramètres!$C$15)) -> 673.09456 | G36: =IF(Paramètres!$C$15="",0,-PMT(Paramètres!$C$16/12,Paramètres!$C$17*12,Paramètres!$C$15)) -> 673.09456 | H36: =IF(Paramètres!$C$15="",0,-PMT(Paramètres!$C$16/12,Paramètres!$C$17*12,Paramètres!$C$15)) -> 673.09456 | I36: =IF(Paramètres!$C$15="",0,-PMT(Paramètres!$C$16/12,Paramètres!$C$17*12,Paramètres!$C$15)) -> 673.09456 | ... M36: =IF(Paramètres!$C$15="",0,-PMT(Paramètres!$C$16/12,Paramètres!$C$17*12,Paramètres!$C$15)) -> 673.09456 | O36: =SUM(B36:M36) -> 8077.1348
A37: IS ou autres selon régime jurid | B37: ='CR pluriannuel '!E11 -> 2282.995 | O37: =SUM(B37:M37) -> 2282.995
A38: DECAISSEMENTS | B38: =SUM(B18:B37) -> 20489.106 | C38: =SUM(C18:C37) -> 18007.629 | D38: =SUM(D18:D37) -> 19903.074 | E38: =SUM(E18:E37) -> 19104.592 | F38: =SUM(F18:F37) -> 18206.111 | G38: =SUM(G18:G37) -> 18804.592 | H38: =SUM(H18:H37) -> 19004.592 | I38: =SUM(I18:I37) -> 19304.592 | ... M38: =SUM(M18:M37) -> 19403.074 | O38: =SUM(B38:M38) -> 228142.66 | P38: =IF(O38=SUM(O18:O37),"ok","non") -> ok
A40: TVA collectée 20% | B40: =B8/1.2*0.2*0.25 -> 39.414375 | C40: =C8/1.2*0.2*0.25 -> 37.5375 | D40: =D8/1.2*0.2*0.25 -> 43.168125 | E40: =E8/1.2*0.2*0.25 -> 41.29125 | F40: =F8/1.2*0.2*0.25 -> 39.414375 | G40: =G8/1.2*0.2*0.25 -> 41.29125 | H40: =H8/1.2*0.2*0.25 -> 41.29125 | I40: =I8/1.2*0.2*0.25 -> 41.29125 | ... M40: =M8/1.2*0.2*0.25 -> 43.168125 | O40: =SUM(B40:M40) -> 489.86438
A41: TVA Collectée 10% | B41: =B7/1.1*0.1+B8/1.1*0.1*0.75 -> 1887.7556 | C41: =C7/1.1*0.1+C8/1.1*0.1*0.75 -> 1797.8625 | D41: =D7/1.1*0.1+D8/1.1*0.1*0.75 -> 2067.5419 | E41: =E7/1.1*0.1+E8/1.1*0.1*0.75 -> 1977.6488 | F41: =F7/1.1*0.1+F8/1.1*0.1*0.75 -> 1887.7556 | G41: =G7/1.1*0.1+G8/1.1*0.1*0.75 -> 1977.6488 | H41: =H7/1.1*0.1+H8/1.1*0.1*0.75 -> 1977.6488 | I41: =I7/1.1*0.1+I8/1.1*0.1*0.75 -> 1977.6488 | ... M41: =M7/1.1*0.1+M8/1.1*0.1*0.75 -> 2067.5419 | O41: =SUM(B41:M41) -> 23462.106
A42: TVA collectée 5,5% | O42: =SUM(B42:M42) -> 0
A43: TVA déductible 20% | B43: =(B16/1.2*0.2)+(B19/1.2*0.2)+(B20/1.2*0.2)+(B21/1.2*0.2*0.25)+(B22/1.2*0.2)+(B25/1.2*0.2)+(B26/1.2*0.2)+(B27/1.2*0.2)+(B28/1.2*0.2)+(B30/1.2*0.2)+(B31/1.2*0.2) -> 326.77909 | C43: =(C16/1.2*0.2)+(C19/1.2*0.2)+(C20/1.2*0.2)+(C21/1.2*0.2*0.25)+(C22/1.2*0.2)+(C25/1.2*0.2)+(C26/1.2*0.2)+(C27/1.2*0.2)+(C28/1.2*0.2)+(C30/1.2*0.2)+(C31/1.2*0.2) -> 380.02771 | D43: =(D16/1.2*0.2)+(D19/1.2*0.2)+(D20/1.2*0.2)+(D21/1.2*0.2*0.25)+(D22/1.2*0.2)+(D25/1.2*0.2)+(D26/1.2*0.2)+(D27/1.2*0.2)+(D28/1.2*0.2)+(D30/1.2*0.2)+(D31/1.2*0.2) -> 436.94853 | E43: =(E16/1.2*0.2)+(E19/1.2*0.2)+(E20/1.2*0.2)+(E21/1.2*0.2*0.25)+(E22/1.2*0.2)+(E25/1.2*0.2)+(E26/1.2*0.2)+(E27/1.2*0.2)+(E28/1.2*0.2)+(E30/1.2*0.2)+(E31/1.2*0.2) -> 390.19715 | F43: =(F16/1.2*0.2)+(F19/1.2*0.2)+(F20/1.2*0.2)+(F21/1.2*0.2*0.25)+(F22/1.2*0.2)+(F25/1.2*0.2)+(F26/1.2*0.2)+(F27/1.2*0.2)+(F28/1.2*0.2)+(F30/1.2*0.2)+(F31/1.2*0.2) -> 326.77909 | G43: =(G16/1.2*0.2)+(G19/1.2*0.2)+(G20/1.2*0.2)+(G21/1.2*0.2*0.25)+(G22/1.2*0.2)+(G25/1.2*0.2)+(G26/1.2*0.2)+(G27/1.2*0.2)+(G28/1.2*0.2)+(G30/1.2*0.2)+(G31/1.2*0.2) -> 340.19715 | H43: =(H16/1.2*0.2)+(H19/1.2*0.2)+(H20/1.2*0.2)+(H21/1.2*0.2*0.25)+(H22/1.2*0.2)+(H25/1.2*0.2)+(H26/1.2*0.2)+(H27/1.2*0.2)+(H28/1.2*0.2)+(H30/1.2*0.2)+(H31/1.2*0.2) -> 373.53048 | I43: =(I16/1.2*0.2)+(I19/1.2*0.2)+(I20/1.2*0.2)+(I21/1.2*0.2*0.25)+(I22/1.2*0.2)+(I25/1.2*0.2)+(I26/1.2*0.2)+(I27/1.2*0.2)+(I28/1.2*0.2)+(I30/1.2*0.2)+(I31/1.2*0.2) -> 423.53048 | ... M43: =(M16/1.2*0.2)+(M19/1.2*0.2)+(M20/1.2*0.2)+(M21/1.2*0.2*0.25)+(M22/1.2*0.2)+(M25/1.2*0.2)+(M26/1.2*0.2)+(M27/1.2*0.2)+(M28/1.2*0.2)+(M30/1.2*0.2)+(M31/1.2*0.2) -> 353.6152 | O43: =SUM(B43:M43) -> 4375.4449
A44: TVA Déductible 10% | O44: =SUM(B44:M44) -> 0
A45: TVA Déductible 5,5% | B45: =(B18/1.055*0.055)+(B21/1.055*0.055*0.75) -> 386.02005 | C45: =(C18/1.055*0.055)+(C21/1.055*0.055*0.75) -> 367.63814 | D45: =(D18/1.055*0.055)+(D21/1.055*0.055*0.75) -> 422.78386 | E45: =(E18/1.055*0.055)+(E21/1.055*0.055*0.75) -> 404.40196 | F45: =(F18/1.055*0.055)+(F21/1.055*0.055*0.75) -> 386.02005 | G45: =(G18/1.055*0.055)+(G21/1.055*0.055*0.75) -> 404.40196 | H45: =(H18/1.055*0.055)+(H21/1.055*0.055*0.75) -> 404.40196 | I45: =(I18/1.055*0.055)+(I21/1.055*0.055*0.75) -> 404.40196 | ... M45: =(M18/1.055*0.055)+(M21/1.055*0.055*0.75) -> 422.78386 | O45: =SUM(B45:M45) -> 4797.6778
A46: Report Crédit de TVA M-1 | C46: =IF(B47<0,B47,"") | D46: =IF(C47<0,C47,"") | E46: =IF(D47<0,D47,"") | F46: =IF(E47<0,E47,"") | G46: =IF(F47<0,F47,"") | H46: =IF(G47<0,G47,"") | I46: =IF(H47<0,H47,"") | J46: =IF(I47<0,I47,"") | ... M46: =IF(L47<0,L47,"") | O46: =SUM(B46:M46) -> 0
A47: Solde de TVA mensuel | B47: =(SUM(B40:B42))-(SUM(B43:B46)) -> 1214.3709 | C47: =(SUM(C40:C42))-(SUM(C43:C45)) -> 1087.7341 | D47: =(SUM(D40:D42))-(SUM(D43:D45)) -> 1250.9776 | E47: =(SUM(E40:E42))-(SUM(E43:E45)) -> 1224.3409 | F47: =(SUM(F40:F42))-(SUM(F43:F45)) -> 1214.3709 | G47: =(SUM(G40:G42))-(SUM(G43:G45)) -> 1274.3409 | H47: =(SUM(H40:H42))-(SUM(H43:H45)) -> 1241.0076 | I47: =(SUM(I40:I42))-(SUM(I43:I45)) -> 1191.0076 | J47: =(SUM(J40:J42))-(SUM(J43:J45)) -> 1274.3409 | ... M47: =(SUM(M40:M42))-(SUM(M43:M45)) -> 1334.3109 | O47: =SUM(B47:M47) -> 14778.847
A48: TVA A DECAISSER | B48: ='Trésorerie année 2'!M47 -> 1215.2723 | C48: =IF(B47>0,B47,0) -> 1214.3709 | D48: =IF(C47>0,C47,0) -> 1087.7341 | E48: =IF(D47>0,D47,0) -> 1250.9776 | F48: =IF(E47>0,E47,0) -> 1224.3409 | G48: =IF(F47>0,F47,0) -> 1214.3709 | H48: =IF(G47>0,G47,0) -> 1274.3409 | I48: =IF(H47>0,H47,0) -> 1241.0076 | J48: =IF(I47>0,I47,0) -> 1191.0076 | ... M48: =IF(L47>0,L47,0) -> 1274.3409
A50: Solde du mois | B50: =B12-(B16+B38+B48) -> -702.57975 | C50: =C12-(C16+C38+C48) -> 779.71283 | D50: =D12-(D16+D38+D48) -> 2011.1613 | E50: =E12-(E16+E38+E48) -> 1646.3139 | F50: =F12-(F16+F38+F48) -> 1571.3467 | G50: =G12-(G16+G38+G48) -> 1982.9207 | H50: =H12-(H16+H38+H48) -> 1722.9506 | I50: =I12-(I16+I38+I48) -> 1456.2839 | ... M50: =M12-(M16+M38+M48) -> 2324.5545
A51: TRESORERIE CUMULEE FIN DE MOIS | B51: =B3+B50 -> 40626.03 | C51: =C3+C50 -> 41405.743 | D51: =D3+D50 -> 43416.904 | E51: =E3+E50 -> 45063.218 | F51: =F3+F50 -> 46634.565 | G51: =G3+G50 -> 48617.485 | H51: =H3+H50 -> 50340.436 | I51: =I3+I50 -> 51796.72 | ... M51: =M3+M50 -> 59548.493

Sheet CR pluriannuel 
C2: Régime fiscal eurl
B3: COMPTES DE RESULTAT PREVISIONNELS | D3: Prévisionnel | E3: Prévisionnel | F3: Prévisionnel
D5: ='Trésorerie année 1'!B1 -> 2025 | E5: =D5+1 -> 2026 | F5: =E5+1 -> 2027
D7: TOTAL | E7: TOTAL | F7: TOTAL
C8: Charges | D8: =SUM(D15,D42,D66,D100,D126,D142,D149,D160,D172,D176) -> 180723.32 | E8: =SUM(E15,E42,E66,E100,E126,E142,E149,E160,E172,E176) -> 199901.13 | F8: =SUM(F15,F42,F66,F100,F126,F142,F149,F160,F172,F176) -> 217712.24
C9: Produits | D9: =SUM(D183,D189,D190,D191,D192,D198,D202) -> 186318.41 | E9: =SUM(E183,E189,E190,E191,E192,E198,E202) -> 215121.09 | F9: =SUM(F183,F189,F190,F191,F192,F198,F202) -> 237070.38
C10: Résultat Net | D10: =D9-D8-D11 -> 4755.8238 | E10: =E9-E8-E11 -> 12936.972 | F10: =F9-F8-F11 -> 16454.42
C11: IS (15% jusqu'à 42500 euros et 25% au-delà) | D11: =IF(D9-D8>42500,((42500*0.15)+((D9-D8-42500)*0.25)),(D9-D8)*0.15) -> 839.26302 | E11: =IF(E9-E8>42500,((42500*0.15)+((E9-E8-42500)*0.25)),(E9-E8)*0.15) -> 2282.995 | F11: =IF(F9-F8>42500,((42500*0.15)+((F9-F8-42500)*0.25)),(F9-F8)*0.15) -> 2903.7213
B12: CHARGES | D12: TOTAL | E12: TOTAL | F12: TOTAL
B15: 60 | C15: ACHATS | D15: =SUM(D16,D19,D20,D23,D34,D38,D39) -> 80138.184 | E15: =SUM(E16,E19,E20,E23,E34,E38,E39) -> 93775.616 | F15: =SUM(F16,F19,F20,F23,F34,F38,F39) -> 105574.4
B16: 602 | C16: ACHATS STOCKES - AUTRES APPROVISIONNEMENTS | D16: =SUM(D17:D18) -> 66021.558 | E16: =SUM(E17:E18) -> 78236.451 | F16: =SUM(F17:F18) -> 88448.826
B17: 602200 | C17: Fournitures consommables | D17: ='Trésorerie année 1'!O18/1.055 -> 63085.308 | E17: ='Trésorerie année 2'!O18/1.055 -> 75006.576 | F17: ='Trésorerie année 3'!O18/1.055 -> 85057.457
B18: 602600 | C18: Emballages | D18: ='Trésorerie année 1'!O19/1.2 -> 2936.25 | E18: ='Trésorerie année 2'!O19/1.2 -> 3229.875 | F18: ='Trésorerie année 3'!O19/1.2 -> 3391.3688
B19: 603 | C19: VARIATIONS DE STOCKS DE MARCHANDISES et APPROVISIONNEMENTS | D19: 0 | E19: 0 | F19: 0
B20: 604 | C20: ACHATS PRESTATIONS DE SERVICE et D'ETUDES | D20: =SUM(D21:D22) -> 1709.55 | E20: =SUM(E21:E22) -> 1973.8125 | F20: =SUM(F21:F22) -> 2175.1862
B21: 604300 | C21: Achat de prestations | D21: ='Trésorerie année 1'!O26/1.2 -> 1709.55 | E21: ='Trésorerie année 2'!O26/1.2 -> 1973.8125 | F21: ='Trésorerie année 3'!O26/1.2 -> 2175.1862
B22: 604400 | C22: Hébergement de site internet (nom de domaine, etc.) | D22: 0 | E22: 0 | F22: 0
B23: 606 | C23: ACHATS NON STOCKES DE MATIERES ET FOURNITURES | D23: =SUM(D24,D29,D32:D33) -> 10334.167 | E23: =SUM(E24,E29,E32:E33) -> 11091.177 | F23: =SUM(F24,F29,F32:F33) -> 12140.513
B24: 606100 | C24: Fournitures non stockables (fluides) | D24: =SUM(D25:D28) -> 8917.5 | E24: =SUM(E25:E28) -> 10257.844 | F24: =SUM(F25:F28) -> 11307.179
B25: 606 110 | C25: Eau | D25: =('Trésorerie année 1'!O22/3)/1.2 -> 2718.75 | E25: =('Trésorerie année 2'!O22/3)/1.2 -> 3140.1563 | F25: =('Trésorerie année 3'!O22/3)/1.2 -> 3462.0223
B26: 606 120 | C26: Electricité | D26: =('Trésorerie année 1'!O22/3)/1.2 -> 2718.75 | E26: =('Trésorerie année 2'!O22/3)/1.2 -> 3140.1563 | F26: =('Trésorerie année 3'!O22/3)/1.2 -> 3462.0223
B27: 606 130 | C27: Gaz | D27: =('Trésorerie année 1'!O22/3)/1.2 -> 2718.75 | E27: =('Trésorerie année 2'!O22/3)/1.2 -> 3140.1563 | F27: =('Trésorerie année 3'!O22/3)/1.2 -> 3462.0223
B28: 606 140 | C28: Carburant | D28: =('Trésorerie année 1'!O20)/1.2 -> 761.25 | E28: =('Trésorerie année 2'!O20)/1.2 -> 837.375 | F28: =('Trésorerie année 3'!O20)/1.2 -> 921.1125
B29: 606 300 | C29: Fournitures d'entretien et de petit équipement | D29: =SUM(D30:D31) -> 0 | E29: =SUM(E30:E31) -> 0 | F29: =SUM(F30:F31) -> 0
B30: 606310 | C30: Fournitures d'entretien | D30: 0 | E30: 0 | F30: 0
B31: 606 320 | C31: Fournitures de petit équipement | D31: 0 | E31: 0 | F31: 0
B32: 606400 | C32: Fournitures administratives | D32: 0 | E32: 0 | F32: 0
B33: 606800 | C33: Autres matières et fournitures diverses | D33: =('Trésorerie année 1'!O27)/1.2 -> 1416.6667 | E33: =('Trésorerie année 2'!O27)/1.2 -> 833.33333 | F33: =('Trésorerie année 3'!O27)/1.2 -> 833.33333
B34: 607 | C34: ACHATS DE MARCHANDISES | D34: =SUM(D35:D37) -> 2072.909 | E34: =SUM(E35:E37) -> 2474.1752 | F34: =SUM(F35:F37) -> 2809.8713
B35: 607100 | C35: Achats de marchandises - taux normal tva 20% | D35: =('Trésorerie année 1'!O21*0.25)/1.2 -> 469.8 | E35: =('Trésorerie année 2'!O21*0.25)/1.2 -> 560.74219 | F35: =('Trésorerie année 3'!O21*0.25)/1.2 -> 636.82369
B36: 607200 | C36: Achats de marchandises - taux intermédiaire 10% | D36: 0 | E36: 0 | F36: 0
B37: 607310 | C37: Achats de marchandises - taux réduit de 5,5% | D37: =('Trésorerie année 1'!O21*0.75)/1.055 -> 1603.109 | E37: =('Trésorerie année 2'!O21*0.75)/1.055 -> 1913.4331 | F37: =('Trésorerie année 3'!O21*0.75)/1.055 -> 2173.0477
B38: 608 | C38: FRAIS ACCESSOIRES D'ACHATS | D38: 0 | E38: 0 | F38: 0
B39: 609 | C39: RABAIS, REMISES, RISTOURNES OBTENUS SUR ACHATS | D39: =SUM(D40:D41) -> 0 | E39: =SUM(E40:E41) -> 0 | F39: =SUM(F40:F41) -> 0
B40: 609400 | C40: Rabais, Remises et Ristounes obtenus sur achats prestations de services | D40: 0 | E40: 0 | F40: 0
B41: 609700 | C41: Rabais, Remises et Ristounes obtenus sur achats de marchandises | D41: 0 | E41: 0 | F41: 0
B42: 61 | C42: SERVICES EXTERIEURS | D42: =SUM(D43,D44,D47,D50,D51,D56,D60,D61,D65) -> 10200 | E42: =SUM(E43,E44,E47,E50,E51,E56,E60,E61,E65) -> 10200 | F42: =SUM(F43,F44,F47,F50,F51,F56,F60,F61,F65) -> 10200
B43: 611 | C43: SOUS TRAITANCE GENERALE | D43: 0 | E43: 0 | F43: 0
B44: 612 | C44: REDEVANCES CREDIT BAIL | D44: =SUM(D45:D46) -> 0 | E44: =SUM(E45:E46) -> 0 | F44: =SUM(F45:F46) -> 0
B45: 612 200 | C45: Crédit-bail mobilier | D45: 0 | E45: 0 | F45: 0
B46: 612 500 | C46: Crédit-bail immobilier | D46: 0 | E46: 0 | F46: 0
B47: 613 | C47: LOCATIONS | D47: =SUM(D48,D49) -> 6000 | E47: =SUM(E48,E49) -> 6000 | F47: =SUM(F48,F49) -> 6000
B48: 613 200 | C48: Locations immobilières | D48: ='Trésorerie année 1'!O24 -> 6000 | E48: ='Trésorerie année 2'!O24 -> 6000 | F48: ='Trésorerie année 3'!O24 -> 6000
B49: 613 500 | C49: Locations mobilières | D49: 0 | E49: 0 | F49: 0
B50: 614 | C50: CHARGES LOCATIVES ET DE COPROPRIETE | D50: 0 | E50: 0 | F50: 0
B51: 615 | C51: ENTRETIENS ET REPARATIONS | D51: =SUM(D52:D55) -> 1500 | E51: =SUM(E52:E55) -> 1500 | F51: =SUM(F52:F55) -> 1500
B52: 615200 | C52: sur biens immobiliers | D52: 0 | E52: 0 | F52: 0
B53: 615 500 | C53: sur biens mobiliers | D53: =('Trésorerie année 1'!O28/2)/1.2 -> 750 | E53: =('Trésorerie année 2'!O28/2)/1.2 -> 750 | F53: =('Trésorerie année 3'!O28/2)/1.2 -> 750
B54: 615 600 | C54: Maintenance | D54: =('Trésorerie année 1'!O28/2)/1.2 -> 750 | E54: =('Trésorerie année 2'!O28/2)/1.2 -> 750 | F54: =('Trésorerie année 3'!O28/2)/1.2 -> 750
B55: 615 700 | C55: Entretien et Réparations - divers | D55: 0 | E55: 0 | F55: 0
B56: 616 | C56: PRIMES D'ASSURANCE | D56: =SUM(D57:D59) -> 2700 | E56: =SUM(E57:E59) -> 2700 | F56: =SUM(F57:F59) -> 2700
B57: 616100 | C57: Primes d'assurances multi risques | D57: ='Trésorerie année 1'!O29/3 -> 900 | E57: ='Trésorerie année 2'!O29/3 -> 900 | F57: ='Trésorerie année 3'!O29/3 -> 900
B58: 616300 | C58: Primes d'assurances - assurances véhicule | D58: ='Trésorerie année 1'!O29/3 -> 900 | E58: ='Trésorerie année 2'!O29/3 -> 900 | F58: ='Trésorerie année 3'!O29/3 -> 900
B59: 616400 | C59: Primes d'assurances - Risque d'exploitation | D59: ='Trésorerie année 1'!O29/3 -> 900 | E59: ='Trésorerie année 2'!O29/3 -> 900 | F59: ='Trésorerie année 3'!O29/3 -> 900
B60: 617 | C60: ETUDES ET RECHERCHES | D60: 0 | E60: 0 | F60: 0
B61: 618 | C61: DIVERS | D61: =SUM(D62:D64) -> 0 | E61: =SUM(E62:E64) -> 0 | F61: =SUM(F62:F64) -> 0
B62: 618100 | C62: Documentation | D62: 0 | E62: 0 | F62: 0
B63: 618 400 | C63: Abonnements | D63: 0 | E63: 0 | F63: 0
B64: 618 500 | C64: Frais de colloques,séminaires, conférences | D64: 0 | E64: 0 | F64: 0
B65: 619 | C65: Rabais, Remises et Ristounes obtenus sur services extérieurs | D65: 0 | E65: 0 | F65: 0
B66: 62 | C66: AUTRES SERVICES EXTERIEURS | D66: =SUM(D67,D68,D77,D83,D87,D92,D95,D96,D99) -> 2153.3333 | E66: =SUM(E67,E68,E77,E83,E87,E92,E95,E96,E99) -> 2153.3333 | F66: =SUM(F67,F68,F77,F83,F87,F92,F95,F96,F99) -> 2153.3333
B67: 621 | C67: PERSONNEL EXTERIEUR | D67: 0 | E67: 0 | F67: 0
B68: 622 | C68: REMUNERATIONS D'INTERMEDIAIRES ET HONORAIRES | D68: =SUM(D69:D72,D75:D76) -> 1000 | E68: =SUM(E69:E72,E75:E76) -> 1000 | F68: =SUM(F69:F72,F75:F76) -> 1000
B69: 622100 | C69: Commissions et courtages sur achats | D69: 0 | E69: 0 | F69: 0
B70: 622200 | C70: Commissions et courtages sur ventes | D70: 0 | E70: 0 | F70: 0
B71: 622 300 | C71: Affacturage et autres | D71: 0 | E71: 0 | F71: 0
B72: 622 600 | C72: Honoraires | D72: =SUM(D73:D74) -> 1000 | E72: =SUM(E73:E74) -> 1000 | F72: =SUM(F73:F74) -> 1000
B73: 622631 | C73: Honoraires experts-comptables | D73: =('Trésorerie année 1'!O31)/1.2 -> 1000 | E73: =('Trésorerie année 2'!O31)/1.2 -> 1000 | F73: =('Trésorerie année 3'!O31)/1.2 -> 1000
B74: 622 670 | C74: Honoraires autres | D74: 0 | E74: 0 | F74: 0
B75: 622700 | C75: Frais d'actes et de contentieux | D75: 0 | E75: 0 | F75: 0
B76: 622800 | C76: Divers autres services extérieurs | D76: 0 | E76: 0 | F76: 0
B77: 623 | C77: PUBLICITE, PUBLICATIONS, RELATIONS PUBLIQUES | D77: =SUM(D78:D82) -> 833.33333 | E77: =SUM(E78:E82) -> 833.33333 | F77: =SUM(F78:F82) -> 833.33333
B78: 623 100 | C78: Annonces et insertions | D78: 0 | E78: 0 | F78: 0
B79: 623 300 | C79: Foires et expositions | D79: 0 | E79: 0 | F79: 0
B80: 623 600 | C80: Catalogues et imprimés | D80: 0 | E80: 0 | F80: 0
B81: 623 700 | C81: Publications | D81: ='Trésorerie année 1'!O30/1.2 -> 833.33333 | E81: ='Trésorerie année 2'!O30/1.2 -> 833.33333 | F81: ='Trésorerie année 3'!O30/1.2 -> 833.33333
B82: 623800 | C82: Divers | D82: 0 | E82: 0 | F82: 0
B83: 624 | C83: FRAIS DE TRANSPORT | D83: =SUM(D84:D86) -> 0 | E83: =SUM(E84:E86) -> 0 | F83: =SUM(F84:F86) -> 0
B84: 624100 | C84: Transport sur achats | D84: 0 | E84: 0 | F84: 0
B85: 624200 | C85: Transport sur ventes | D85: 0 | E85: 0 | F85: 0
B86: 624 800 | C86: Transport divers | D86: 0 | E86: 0 | F86: 0
B87: 625 | C87: DEPLACEMENTS - MISSIONS ET RECEPTIONS | D87: =SUM(D88:D88,D89:D91) -> 0 | E87: =SUM(E88:E88,E89:E91) -> 0 | F87: =SUM(F88:F88,F89:F91) -> 0
B88: 625100 | C88: Déplacements, voyages | D88: 0 | E88: 0 | F88: 0
B89: 625 500 | C89: Frais de déménagements | D89: 0 | E89: 0 | F89: 0
B90: 625 600 | C90: Missions | D90: 0 | E90: 0 | F90: 0
B91: 625 700 | C91: Réceptions | D91: 0 | E91: 0 | F91: 0
B92: 626 | C92: FRAIS POSTAUX ET DE TELECOMMUNICATION | D92: =SUM(D93:D94) -> 200 | E92: =SUM(E93:E94) -> 200 | F92: =SUM(F93:F94) -> 200
B93: 626100 | C93: Affranchissements / Frais postaux | D93: 0 | E93: 0 | F93: 0
B94: 626200 | C94: Téléphone, Internet | D94: =('Trésorerie année 1'!O25)/1.2 -> 200 | E94: =('Trésorerie année 2'!O25)/1.2 -> 200 | F94: =('Trésorerie année 3'!O25)/1.2 -> 200
B95: 627 | C95: SERVICES BANCAIRES ET ASSIMILES | D95: ='Trésorerie année 1'!O35 -> 120 | E95: ='Trésorerie année 2'!O35 -> 120 | F95: ='Trésorerie année 3'!O35 -> 120
B96: 628 | C96: DIVERS | D96: =SUM(D97,D98) -> 0 | E96: =SUM(E97,E98) -> 0 | F96: =SUM(F97,F98) -> 0
B97: 628 100 | C97: Concours divers (cotisations, etc) | D97: 0 | E97: 0 | F97: 0
B98: 628 400 | C98: Frais de recrutement de personnel | D98: 0 | E98: 0 | F98: 0
B99: 629 | C99: Rabais, Remises et Ristounes obtenus sur autres services extérieurs | D99: 0 | E99: 0 | F99: 0
B100: 63 | C100: IMPOTS, TAXES ET VERSEMENTS ASSIMILES | D100: =SUM(D101,D107,D114,D125) -> 39150 | E100: =SUM(E101,E107,E114,E125) -> 41107.5 | F100: =SUM(F101,F107,F114,F125) -> 43162.875
B101: 631 | C101: IMPOTS, TAXES ET VERSEMENTS ASSIMILES SUR REMUNERATIONS (administratif des impôts) | D101: =SUM(D102:D106) -> 0 | E101: =SUM(E102:E106) -> 0 | F101: =SUM(F102:F106) -> 0
B102: 631100 | C102: Taxe sur salaires | D102: 0 | E102: 0 | F102: 0
B103: 631200 | C103: Taxe d'apprentissage | D103: 0 | E103: 0 | F103: 0
B104: 631300 | C104: Participation des employeurs à l'effort de construction | D104: 0 | E104: 0 | F104: 0
B105: 631400 | C105: Cotisation pour défaut d'investissement obligatoire dans la construction | D105: 0 | E105: 0 | F105: 0
...

Sheet Bilan année 1
D2: Bilan au 31/12/2025
B5: ACTIF | G5: PASSIF
B6: ACTIF IMMOBILISE | D6: BRUT | E6: AMORT. (28) & DEP (29) | F6: NET | G6: CAPITAUX PROPRES | I6: NET
B7: 20 | C7: Immobilisations Incorporelles | D7: =SUM(D8:D12) -> 1666.6667 | E7: =SUM(E8:E12) -> 416.66667 | F7: =D7-E7 -> 1250 | G7: 101 | H7: Capital | I7: ='Plan de financement initial'!H7 -> 22000
B8: 201 | C8: Frais d'établissement | D8: =('Plan de financement initial'!D7)/1.2 -> 1041.6667 | E8: =D8/5 -> 208.33333 | F8: =D8-E8 -> 833.33333 | G8: 1061 | H8: Réserve légale | I8: 0
B9: 203 | C9: Frais de recherche & développement | D9: 0 | E9: 0 | F9: =D9-E9 -> 0 | G9: 1063 | H9: Réserve statutaire | I9: 0
B10: 205 | C10: Concesions, brevets | D10: ='Plan de financement initial'!D16 -> 0 | E10: 0 | F10: =D10-E10 -> 0 | G10: 1064 | H10: Réserves réglementées | I10: 0
B11: 207 | C11: Fonds commercial | D11: ='Plan de financement initial'!D19 -> 0 | E11: 0 | F11: =D11-E11 -> 0 | G11: 1068 | H11: Autres Réserves | I11: 0
B12: 208 | C12: Autres immobilisations incorporelles | D12: =('Plan de financement initial'!D17+'Plan de financement initial'!D18)/1.2 -> 625 | E12: =D12/3 -> 208.33333 | F12: =D12-E12 -> 416.66667 | G12: 11 | H12: Report à nouveau (créditeur ou débiteur) | I12: 0
B13: 21 | C13: Immobilisations Corporelles | D13: =SUM(D14:D17) -> 40000 | E13: =SUM(E14:E17) -> 8000 | F13: =D13-E13 -> 32000 | G13: 12 | H13: Résultat de l'exercice | I13: ='CR pluriannuel '!D10 -> 4755.8238
B14: 211 | C14: Terrains | D14: ='Plan de financement initial'!D27 -> 0 | E14: 0 | F14: =D14-E14 -> 0 | G14: 13 | H14: Subvention d'investissement | I14: 0
B15: 213 | C15: Constructions | D15: ='Plan de financement initial'!D28+'Plan de financement initial'!D22 -> 0 | E15: 0 | F15: =D15-E15 -> 0 | G15: 14 | H15: Provisions réglementées | I15: 0
B16: 215 | C16: Installations techniques, matériel et outillage industriel | D16: =('Plan de financement initial'!D25+'Plan de financement initial'!D24+'Plan de financement initial'!D26)/1.2 -> 7500 | E16: =D16/5 -> 1500 | F16: =D16-E16 -> 6000 | G16: Total I | I16: =SUM(I7:I15) -> 26755.824
B17: 218 | C17: Autres immobilisations corporelles | D17: =('Plan de financement initial'!D23)/1.2 -> 32500 | E17: =D17/5 -> 6500 | F17: =D17-E17 -> 26000 | G17: 151 | H17: Provisions pour risques | I17: 0
C18: Immobilisations financières | D18: =SUM(D19:D23) -> 0 | E18: =SUM(E19:E23) -> 0 | F18: =D18-E18 -> 0 | G18: 157 | H18: Provisions pour charges | I18: 0
B19: 261 | C19: Titres de Participations | D19: 0 | E19: 0 | F19: =D19-E19 -> 0 | G19: 158 | H19: Autres Provisions pour charges | I19: 0
B20: 267 | C20: Créances rattachées à des participations | D20: 0 | E20: 0 | F20: =D20-E20 -> 0 | G20: Total II | I20: =SUM(I17:I19) -> 0
B21: 271 | C21: Autres titres immobilisés | D21: 0 | E21: 0 | F21: =D21-E21 -> 0 | G21: PASSIF CIRCULANT | I21: NET
B22: 274 | C22: Prêts | D22: 0 | E22: 0 | G22: 163 | H22: Autres emprunts obligataires | I22: 0
B23: 276 | C23: Autres créances immobilisées | D23: ='Plan de financement initial'!D30+'Plan de financement initial'!D31 -> 0 | E23: 0 | F23: =D23-E23 -> 0 | G23: 164 | H23: Emprunts et dettes établissements de crédit (1) | I23: =Emprunt!J29 -> 30108.004
B24: Total I | D24: =D7+D13+D18 -> 41666.667 | E24: =E7+E13+E18 -> 8416.6667 | F24: =F7+F13+F18 -> 33250 | G24: 166 | H24: Participation des salariés aux résultats | I24: 0
B25: ACTIF CIRCULANT | D25: BRUT | E25: DEP. (39/49/59) | F25: NET | G25: 168 | H25: Autres emprunts et dettes assimilées financières | I25: 0
B26: 31 | C26: Stocks MP | D26: 0 | E26: 0 | F26: =D26-E26 -> 0 | G26: 401/403 | H26: Dettes fournisseurs | I26: 0
B27: 32 | C27: Stocks autres approv. | D27: 0 | E27: 0 | F27: =D27-E27 -> 0 | G27: 404 | H27: Dette fournisseurs immobilisations | I27: 0
B28: 33/34 | C28: Stocks En-cours | D28: 0 | E28: 0 | F28: =D28-E28 -> 0 | G28: 419 | H28: Avances et acomptes reçus | I28: 0
B29: 35 | C29: Stocks de Produits | D29: 0 | E29: 0 | F29: =D29-E29 -> 0 | G29: 42 | H29: Dettes charges de personnel | I29: 0
B30: 37 | C30: Stocks de Marchandises | D30: 0 | E30: 0 | F30: =D30-E30 -> 0 | G30: 43 | H30: Dettes de sécurité sociale et autres org soc | I30: 0
B31: 409 | C31: Avances et acomptes versés | D31: 0 | E31: 0 | F31: =D31-E31 -> 0 | G31: 44 | H31: Dettes de l'Etat et CP | I31: ='Trésorerie année 1'!M47+'CR pluriannuel '!D11 -> 1892.5446
B32: 411/413/416/418 | C32: Créances clients | D32: 0 | E32: 0 | F32: =D32-E32 -> 0 | G32: 46 | H32: Autres dettes | I32: 0
B33: 50 | C33: Valeurs mobilières de placement | D33: 0 | E33: 0 | F33: =D33-E33 -> 0 | G33: 487 | H33: Produits constatés d'avance | I33: 0
B34: 51/53 | C34: Disponibilités | D34: ='Trésorerie année 1'!M51 -> 25506.372 | E34: 0 | F34: =D34-E34 -> 25506.372
B35: 486 | C35: Charges constatées d'avance | E35: 0 | F35: =D35-E35 -> 0
B36: Total II | D36: =SUM(D26:D35) -> 25506.372 | E36: =SUM(E26:E35) -> 0 | F36: =SUM(F26:F35) -> 25506.372 | G36: Total III | I36: =SUM(I22:I33) -> 32000.548
B37: TOTAL GENERAL (I + II) | D37: =D24+D36 -> 67173.039 | E37: =E24+E36 -> 8416.6667 | F37: =F24+F36 -> 58756.372 | G37: TOTAL GENERAL (I + II + III) | I37: =I16+I20+I36 -> 58756.372
I39: =F37-I37 -> 0
H41: (1) dont soldes créditeurs de banques :

Sheet Bilan année 2
D2: Bilan au 31/12/2026
B5: ACTIF | G5: PASSIF
B6: ACTIF IMMOBILISE | D6: BRUT | E6: AMORT. (28) & DEP (29) | F6: NET | G6: CAPITAUX PROPRES | I6: NET
B7: 20 | C7: Immobilisations Incorporelles | D7: =SUM(D8:D12) -> 1666.6667 | E7: =SUM(E8:E12) -> 833.33333 | F7: =D7-E7 -> 833.33333 | G7: 101 | H7: Capital | I7: ='Plan de financement initial'!H7 -> 22000
B8: 201 | C8: Frais d'établissement | D8: =('Plan de financement initial'!D7)/1.2 -> 1041.6667 | E8: =(D8/5)*2 -> 416.66667 | F8: =D8-E8 -> 625 | G8: 1061 | H8: Réserve légale | I8: ='Bilan année 1'!I13 -> 4755.8238
B9: 203 | C9: Frais de recherche & développement | D9: 0 | E9: 0 | F9: =D9-E9 -> 0 | G9: 1063 | H9: Réserve statutaire | I9: 0
B10: 205 | C10: Concesions, brevets | D10: ='Plan de financement initial'!D16 -> 0 | E10: 0 | F10: =D10-E10 -> 0 | G10: 1064 | H10: Réserves réglementées | I10: 0
B11: 207 | C11: Fonds commercial | D11: ='Plan de financement initial'!D19 -> 0 | E11: 0 | F11: =D11-E11 -> 0 | G11: 1068 | H11: Autres Réserves | I11: 0
B12: 208 | C12: Autres immobilisations incorporelles | D12: =('Plan de financement initial'!D17+'Plan de financement initial'!D18)/1.2 -> 625 | E12: =(D12/3)*2 -> 416.66667 | F12: =D12-E12 -> 208.33333 | G12: 11 | H12: Report à nouveau (créditeur ou débiteur) | I12: 0
B13: 21 | C13: Immobilisations Corporelles | D13: =SUM(D14:D17) -> 40000 | E13: =SUM(E14:E17) -> 16000 | F13: =D13-E13 -> 24000 | G13: 12 | H13: Résultat de l'exercice | I13: ='CR pluriannuel '!E10 -> 12936.972
B14: 211 | C14: Terrains | D14: ='Plan de financement initial'!D27 -> 0 | E14: 0 | F14: =D14-E14 -> 0 | G14: 13 | H14: Subvention d'investissement | I14: 0
B15: 213 | C15: Constructions | D15: ='Plan de financement initial'!D28+'Plan de financement initial'!D22 -> 0 | E15: 0 | F15: =D15-E15 -> 0 | G15: 14 | H15: Provisions réglementées | I15: 0
B16: 215 | C16: Installations techniques, matériel et outillage industriel | D16: =('Plan de financement initial'!D25+'Plan de financement initial'!D24+'Plan de financement initial'!D26)/1.2 -> 7500 | E16: =(D16/5)*2 -> 3000 | F16: =D16-E16 -> 4500 | G16: Total I | I16: =SUM(I7:I15) -> 39692.796
B17: 218 | C17: Autres immobilisations corporelles | D17: =('Plan de financement initial'!D23)/1.2 -> 32500 | E17: =(D17/5)*2 -> 13000 | F17: =D17-E17 -> 19500 | G17: 151 | H17: Provisions pour risques | I17: 0
C18: Immobilisations financières | D18: =SUM(D19:D23) -> 0 | E18: =SUM(E19:E23) -> 0 | F18: =D18-E18 -> 0 | G18: 157 | H18: Provisions pour charges | I18: 0
B19: 261 | C19: Titres de Participations | D19: 0 | E19: 0 | F19: =D19-E19 -> 0 | G19: 158 | H19: Autres Provisions pour charges | I19: 0
B20: 267 | C20: Créances rattachées à des participations | D20: 0 | E20: 0 | F20: =D20-E20 -> 0 | G20: Total II | I20: =SUM(I17:I19) -> 0
B21: 271 | C21: Autres titres immobilisés | D21: 0 | E21: 0 | F21: =D21-E21 -> 0 | G21: PASSIF CIRCULANT | I21: NET
B22: 274 | C22: Prêts | D22: 0 | E22: 0 | G22: 163 | H22: Autres emprunts obligataires | I22: 0
B23: 276 | C23: Autres créances immobilisées | D23: ='Plan de financement initial'!D30+'Plan de financement initial'!D31 -> 0 | E23: 0 | F23: =D23-E23 -> 0 | G23: 164 | H23: Emprunts et dettes établissements de crédit (1) | I23: =Emprunt!J41 -> 22970.88
B24: Total I | D24: =D7+D13+D18 -> 41666.667 | E24: =E7+E13+E18 -> 16833.333 | F24: =F7+F13+F18 -> 24833.333 | G24: 166 | H24: Participation des salariés aux résultats | I24: 0
B25: ACTIF CIRCULANT | D25: BRUT | E25: DEP. (39/49/59) | F25: NET | G25: 168 | H25: Autres emprunts et dettes assimilées financières | I25: 0
B26: 31 | C26: Stocks MP | D26: 0 | E26: 0 | F26: =D26-E26 -> 0 | G26: 401/403 | H26: Dettes fournisseurs | I26: 0
B27: 32 | C27: Stocks autres approv. | D27: 0 | E27: 0 | F27: =D27-E27 -> 0 | G27: 404 | H27: Dette fournisseurs immobilisations | I27: 0
B28: 33/34 | C28: Stocks En-cours | D28: 0 | E28: 0 | F28: =D28-E28 -> 0 | G28: 419 | H28: Avances et acomptes reçus | I28: 0
B29: 35 | C29: Stocks de Produits | D29: 0 | E29: 0 | F29: =D29-E29 -> 0 | G29: 42 | H29: Dettes charges de personnel | I29: 0
B30: 37 | C30: Stocks de Marchandises | D30: 0 | E30: 0 | F30: =D30-E30 -> 0 | G30: 43 | H30: Dettes de sécurité sociale et autres org soc | I30: 0
B31: 409 | C31: Avances et acomptes versés | D31: 0 | E31: 0 | F31: =D31-E31 -> 0 | G31: 44 | H31: Dettes de l'Etat et CP | I31: ='Trésorerie année 2'!M47+'CR pluriannuel '!E11 -> 3498.2673
B32: 411/413/416/418 | C32: Créances clients | D32: 0 | E32: 0 | F32: =D32-E32 -> 0 | G32: 46 | H32: Autres dettes | I32: 0
B33: 50 | C33: Valeurs mobilières de placement | D33: 0 | E33: 0 | F33: =D33-E33 -> 0 | G33: 487 | H33: Produits constatés d'avance | I33: 0
B34: 51/53 | C34: Disponibilités | D34: ='Trésorerie année 2'!M51 -> 41328.61 | E34: 0 | F34: =D34-E34 -> 41328.61
B35: 486 | C35: Charges constatées d'avance | E35: 0 | F35: =D35-E35 -> 0
B36: Total II | D36: =SUM(D26:D35) -> 41328.61 | E36: =SUM(E26:E35) -> 0 | F36: =SUM(F26:F35) -> 41328.61 | G36: Total III | I36: =SUM(I22:I33) -> 26469.148
B37: TOTAL GENERAL (I + II) | D37: =D24+D36 -> 82995.277 | E37: =E24+E36 -> 16833.333 | F37: =F24+F36 -> 66161.943 | G37: TOTAL GENERAL (I + II + III) | I37: =I16+I20+I36 -> 66161.943
I39: =F37-I37 -> 0
H41: (1) dont soldes créditeurs de banques :

Sheet Bilan année 3
D2: Bilan au 31/12/2027
B5: ACTIF | G5: PASSIF
B6: ACTIF IMMOBILISE | D6: BRUT | E6: AMORT. (28) & DEP (29) | F6: NET | G6: CAPITAUX PROPRES | I6: NET
B7: 20 | C7: Immobilisations Incorporelles | D7: =SUM(D8:D12) -> 1666.6667 | E7: =SUM(E8:E12) -> 1250 | F7: =D7-E7 -> 416.66667 | G7: 101 | H7: Capital | I7: ='Plan de financement initial'!H7 -> 22000
B8: 201 | C8: Frais d'établissement | D8: =('Plan de financement initial'!D7)/1.2 -> 1041.6667 | E8: =(D8/5)*3 -> 625 | F8: =D8-E8 -> 416.66667 | G8: 1061 | H8: Réserve légale | I8: ='Bilan année 2'!I8+'Bilan année 2'!I13 -> 17692.796
B9: 203 | C9: Frais de recherche & développement | D9: 0 | E9: 0 | F9: =D9-E9 -> 0 | G9: 1063 | H9: Réserve statutaire | I9: 0
B10: 205 | C10: Concesions, brevets | D10: ='Plan de financement initial'!D16 -> 0 | E10: 0 | F10: =D10-E10 -> 0 | G10: 1064 | H10: Réserves réglementées | I10: 0
B11: 207 | C11: Fonds commercial | D11: ='Plan de financement initial'!D19 -> 0 | E11: 0 | F11: =D11-E11 -> 0 | G11: 1068 | H11: Autres Réserves | I11: 0
B12: 208 | C12: Autres immobilisations incorporelles | D12: =('Plan de financement initial'!D17+'Plan de financement initial'!D18)/1.2 -> 625 | E12: =(D12/3)*3 -> 625 | F12: =D12-E12 -> 0 | G12: 11 | H12: Report à nouveau (créditeur ou débiteur) | I12: 0
B13: 21 | C13: Immobilisations Corporelles | D13: =SUM(D14:D17) -> 40000 | E13: =SUM(E14:E17) -> 24000 | F13: =D13-E13 -> 16000 | G13: 12 | H13: Résultat de l'exercice | I13: ='CR pluriannuel '!F10 -> 16454.42
B14: 211 | C14: Terrains | D14: ='Plan de financement initial'!D27 -> 0 | E14: 0 | F14: =D14-E14 -> 0 | G14: 13 | H14: Subvention d'investissement | I14: 0
B15: 213 | C15: Constructions | D15: ='Plan de financement initial'!D28+'Plan de financement initial'!D22 -> 0 | E15: 0 | F15: =D15-E15 -> 0 | G15: 14 | H15: Provisions réglementées | I15: 0
B16: 215 | C16: Installations techniques, matériel et outillage industriel | D16: =('Plan de financement initial'!D25+'Plan de financement initial'!D24+'Plan de financement initial'!D26)/1.2 -> 7500 | E16: =(D16/5)*3 -> 4500 | F16: =D16-E16 -> 3000 | G16: Total I | I16: =SUM(I7:I15) -> 56147.216
B17: 218 | C17: Autres immobilisations corporelles | D17: =('Plan de financement initial'!D23)/1.2 -> 32500 | E17: =(D17/5)*3 -> 19500 | F17: =D17-E17 -> 13000 | G17: 151 | H17: Provisions pour risques | I17: 0
C18: Immobilisations financières | D18: =SUM(D19:D23) -> 0 | E18: =SUM(E19:E23) -> 0 | F18: =D18-E18 -> 0 | G18: 157 | H18: Provisions pour charges | I18: 0
B19: 261 | C19: Titres de Participations | D19: 0 | E19: 0 | F19: =D19-E19 -> 0 | G19: 158 | H19: Autres Provisions pour charges | I19: 0
B20: 267 | C20: Créances rattachées à des participations | D20: 0 | E20: 0 | F20: =D20-E20 -> 0 | G20: Total II | I20: =SUM(I17:I19) -> 0
B21: 271 | C21: Autres titres immobilisés | D21: 0 | E21: 0 | F21: =D21-E21 -> 0 | G21: PASSIF CIRCULANT | I21: NET
B22: 274 | C22: Prêts | D22: 0 | E22: 0 | G22: 163 | H22: Autres emprunts obligataires | I22: 0
B23: 276 | C23: Autres créances immobilisées | D23: ='Plan de financement initial'!D30+'Plan de financement initial'!D31 -> 0 | E23: 0 | F23: =D23-E23 -> 0 | G23: 164 | H23: Emprunts et dettes établissements de crédit (1) | I23: =Emprunt!J53 -> 15579.911
B24: Total I | D24: =D7+D13+D18 -> 41666.667 | E24: =E7+E13+E18 -> 25250 | F24: =F7+F13+F18 -> 16416.667 | G24: 166 | H24: Participation des salariés aux résultats | I24: 0
B25: ACTIF CIRCULANT | D25: BRUT | E25: DEP. (39/49/59) | F25: NET | G25: 168 | H25: Autres emprunts et dettes assimilées financières | I25: 0
B26: 31 | C26: Stocks MP | D26: 0 | E26: 0 | F26: =D26-E26 -> 0 | G26: 401/403 | H26: Dettes fournisseurs | I26: 0
B27: 32 | C27: Stocks autres approv. | D27: 0 | E27: 0 | F27: =D27-E27 -> 0 | G27: 404 | H27: Dette fournisseurs immobilisations | I27: 0
B28: 33/34 | C28: Stocks En-cours | D28: 0 | E28: 0 | F28: =D28-E28 -> 0 | G28: 419 | H28: Avances et acomptes reçus | I28: 0
B29: 35 | C29: Stocks de Produits | D29: 0 | E29: 0 | F29: =D29-E29 -> 0 | G29: 42 | H29: Dettes charges de personnel | I29: 0
B30: 37 | C30: Stocks de Marchandises | D30: 0 | E30: 0 | F30: =D30-E30 -> 0 | G30: 43 | H30: Dettes de sécurité sociale et autres org soc | I30: 0
B31: 409 | C31: Avances et acomptes versés | D31: 0 | E31: 0 | F31: =D31-E31 -> 0 | G31: 44 | H31: Dettes de l'Etat et CP | I31: ='Trésorerie année 3'!M47+'CR pluriannuel '!F11 -> 4238.0322
B32: 411/413/416/418 | C32: Créances clients | D32: 0 | E32: 0 | F32: =D32-E32 -> 0 | G32: 46 | H32: Autres dettes | I32: 0
B33: 50 | C33: Valeurs mobilières de placement | D33: 0 | E33: 0 | F33: =D33-E33 -> 0 | G33: 487 | H33: Produits constatés d'avance | I33: 0
B34: 51/53 | C34: Disponibilités | D34: ='Trésorerie année 3'!M51 -> 59548.493 | E34: 0 | F34: =D34-E34 -> 59548.493
B35: 486 | C35: Charges constatées d'avance | E35: 0 | F35: =D35-E35 -> 0
B36: Total II | D36: =SUM(D26:D35) -> 59548.493 | E36: =SUM(E26:E35) -> 0 | F36: =SUM(F26:F35) -> 59548.493 | G36: Total III | I36: =SUM(I22:I33) -> 19817.943
B37: TOTAL GENERAL (I + II) | D37: =D24+D36 -> 101215.16 | E37: =E24+E36 -> 25250 | F37: =F24+F36 -> 75965.159 | G37: TOTAL GENERAL (I + II + III) | I37: =I16+I20+I36 -> 75965.159
I39: =F37-I37 -> 1.3096724e-10
H41: (1) dont soldes créditeurs de banques :

Sheet Plan de financement initial
B2: PLAN DE FINANCEMENT INITIAL
B5: BESOINS | F5: RESSOURCES
B7: Frais d'établissement | D7: =SUM(D8:D12) -> 1250 | F7: Apports en capital social | H7: =SUM(H8:H10) -> 22000
B8: Frais d'enregistrement | D8: 500 | F8: Capital - porteur de projet | H8: 22000
B9: Honoraires | D9: 0 | F9: Capital - associé | H9: 0
B10: Dépôt de marque INPI | D10: 0 | F10: Capital - Business Angel | H10: 0
B11: Publicité au démarrage | D11: 750
B12: Droit d'entrée franchise | D12: 0
F13: Comptes courants d'associés | H13: 0
F14: (s'il y a lieu *)
B15: Immobilisations incorporelles | D15: =SUM(D16:D20) -> 750
B16: Brevet, licences | D16: 0 | F16: Subvention d'investissement | H16: 0
B17: Création site internet | D17: 750
B18: Logiciel | D18: 0
B19: Fonds de commerce ou droit au bail | D19: 0 | F19: Prêts d'honneur | H19: 0
B21: Immobilisations corporelles | D21: =SUM(D22:D28) -> 48000
B22: Travaux / aménagements | D22: 0
B23: Véhicule | D23: 39000
B24: Mobilier | D24: 0 | F24: PCE | H24: 0
B25: Matériel (informatique, électrogène, autres) | D25: =6000+500+2500 -> 9000
B26: Outillage | D26: 0
B27: Terrain | D27: 0
B28: Construction | D28: 0
B29: Immobilisations financières | D29: =SUM(D30:D31) -> 0
B30: Garanties sur loyers | D30: 0 | F30: Emprunts à moyen ou long terme | H30: 37000
B31: Garanties professionnelles | D31: 0
B34: Stock de marchandises | D34: ='Trésorerie année 1'!B18+'Trésorerie année 1'!B21+'Trésorerie année 1'!B19 -> 6374.22
B35: Créances clients (s'il y a lieu) | D35: 0
B37: Tresorerie - Disponibilités | D37: =H40-SUM(D35,D34,D29,D21,D15,D7) -> 2625.78
B38: (ou fonds de caisse)
B40: TOTAL | D40: =D7+D15+D21+D29+D34+D35+D37 -> 59000 | F40: TOTAL | H40: =SUM(H7,H13,H16,H19,H24,H30) -> 59000

Sheet Emprunt
B2: TABLEAU D'AMORTISSEMENT D'UN EMPRUNT
B5: Caratéristiques de l'emprunt
B6: Montant emprunté | C6: =Paramètres!C15 -> 37000
B7: taux intérêt annuel | C7: =Paramètres!C16 -> 0.035
B8: Durée (ans) | C8: =Paramètres!C17 -> 5
B9: Date de début (JJ/MM/AAAA) | C9: 45658
B11: Vue globale de l'emprunt
B12: Nombre de mensualités | C12: =C8*12 -> 60
B13: Montant mensuel | C13: =PMT(C7/12,C12,-C6) -> 673.09456
B14: Total versements | C14: =C13*C12 -> 40385.674
B15: Coût total | C15: =C14-C6 -> 3385.6738
D17: Échéance | E17: Date | F17: Capital amorti | G17: Mensualité de remboursement | H17: Intérêts | I17: Capital | J17: Capital restant dû
D18: 1 | E18: =EOMONTH(C9,0) -> 45688 | F18: =C6 -> 37000 | G18: =IF(D18="","",$C$13) -> 673.09456 | H18: =IF(D18="","",F18*$C$7/12) -> 107.91667 | I18: =IF(D18="","",G18-H18) -> 565.1779 | J18: =IF(D18="","",F18-I18) -> 36434.822
D19: =IFERROR(IF(D18+1<=$C$12,D18+1,""),"") -> 2 | E19: =IF(D19="","",EOMONTH(E18,1)) -> 45716 | F19: =IF(D19="","",J18) -> 36434.822 | G19: =IF(D19="","",$C$13) -> 673.09456 | H19: =IF(D19="","",F19*$C$7/12) -> 106.26823 | I19: =IF(D19="","",G19-H19) -> 566.82633 | J19: =IF(D19="","",F19-I19) -> 35867.996
D20: =IFERROR(IF(D19+1<=$C$12,D19+1,""),"") -> 3 | E20: =IF(D20="","",EOMONTH(E19,1)) -> 45747 | F20: =IF(D20="","",J19) -> 35867.996 | G20: =IF(D20="","",$C$13) -> 673.09456 | H20: =IF(D20="","",F20*$C$7/12) -> 104.61499 | I20: =IF(D20="","",G20-H20) -> 568.47958 | J20: =IF(D20="","",F20-I20) -> 35299.516
D21: =IFERROR(IF(D20+1<=$C$12,D20+1,""),"") -> 4 | E21: =IF(D21="","",EOMONTH(E20,1)) -> 45777 | F21: =IF(D21="","",J20) -> 35299.516 | G21: =IF(D21="","",$C$13) -> 673.09456 | H21: =IF(D21="","",F21*$C$7/12) -> 102.95692 | I21: =IF(D21="","",G21-H21) -> 570.13764 | J21: =IF(D21="","",F21-I21) -> 34729.379
D22: =IFERROR(IF(D21+1<=$C$12,D21+1,""),"") -> 5 | E22: =IF(D22="","",EOMONTH(E21,1)) -> 45808 | F22: =IF(D22="","",J21) -> 34729.379 | G22: =IF(D22="","",$C$13) -> 673.09456 | H22: =IF(D22="","",F22*$C$7/12) -> 101.29402 | I22: =IF(D22="","",G22-H22) -> 571.80054 | J22: =IF(D22="","",F22-I22) -> 34157.578
D23: =IFERROR(IF(D22+1<=$C$12,D22+1,""),"") -> 6 | E23: =IF(D23="","",EOMONTH(E22,1)) -> 45838 | F23: =IF(D23="","",J22) -> 34157.578 | G23: =IF(D23="","",$C$13) -> 673.09456 | H23: =IF(D23="","",F23*$C$7/12) -> 99.626269 | I23: =IF(D23="","",G23-H23) -> 573.46829 | J23: =IF(D23="","",F23-I23) -> 33584.11
D24: =IFERROR(IF(D23+1<=$C$12,D23+1,""),"") -> 7 | E24: =IF(D24="","",EOMONTH(E23,1)) -> 45869 | F24: =IF(D24="","",J23) -> 33584.11 | G24: =IF(D24="","",$C$13) -> 673.09456 | H24: =IF(D24="","",F24*$C$7/12) -> 97.953653 | I24: =IF(D24="","",G24-H24) -> 575.14091 | J24: =IF(D24="","",F24-I24) -> 33008.969
D25: =IFERROR(IF(D24+1<=$C$12,D24+1,""),"") -> 8 | E25: =IF(D25="","",EOMONTH(E24,1)) -> 45900 | F25: =IF(D25="","",J24) -> 33008.969 | G25: =IF(D25="","",$C$13) -> 673.09456 | H25: =IF(D25="","",F25*$C$7/12) -> 96.276159 | I25: =IF(D25="","",G25-H25) -> 576.8184 | J25: =IF(D25="","",F25-I25) -> 32432.15
D26: =IFERROR(IF(D25+1<=$C$12,D25+1,""),"") -> 9 | E26: =IF(D26="","",EOMONTH(E25,1)) -> 45930 | F26: =IF(D26="","",J25) -> 32432.15 | G26: =IF(D26="","",$C$13) -> 673.09456 | H26: =IF(D26="","",F26*$C$7/12) -> 94.593772 | I26: =IF(D26="","",G26-H26) -> 578.50079 | J26: =IF(D26="","",F26-I26) -> 31853.65
D27: =IFERROR(IF(D26+1<=$C$12,D26+1,""),"") -> 10 | E27: =IF(D27="","",EOMONTH(E26,1)) -> 45961 | F27: =IF(D27="","",J26) -> 31853.65 | G27: =IF(D27="","",$C$13) -> 673.09456 | H27: =IF(D27="","",F27*$C$7/12) -> 92.906478 | I27: =IF(D27="","",G27-H27) -> 580.18809 | J27: =IF(D27="","",F27-I27) -> 31273.462
D28: =IFERROR(IF(D27+1<=$C$12,D27+1,""),"") -> 11 | E28: =IF(D28="","",EOMONTH(E27,1)) -> 45991 | F28: =IF(D28="","",J27) -> 31273.462 | G28: =IF(D28="","",$C$13) -> 673.09456 | H28: =IF(D28="","",F28*$C$7/12) -> 91.214263 | I28: =IF(D28="","",G28-H28) -> 581.8803 | J28: =IF(D28="","",F28-I28) -> 30691.581
D29: =IFERROR(IF(D28+1<=$C$12,D28+1,""),"") -> 12 | E29: =IF(D29="","",EOMONTH(E28,1)) -> 46022 | F29: =IF(D29="","",J28) -> 30691.581 | G29: =IF(D29="","",$C$13) -> 673.09456 | H29: =IF(D29="","",F29*$C$7/12) -> 89.517112 | I29: =IF(D29="","",G29-H29) -> 583.57745 | J29: =IF(D29="","",F29-I29) -> 30108.004
D30: =IFERROR(IF(D29+1<=$C$12,D29+1,""),"") -> 13 | E30: =IF(D30="","",EOMONTH(E29,1)) -> 46053 | F30: =IF(D30="","",J29) -> 30108.004 | G30: =IF(D30="","",$C$13) -> 673.09456 | H30: =IF(D30="","",F30*$C$7/12) -> 87.815011 | I30: =IF(D30="","",G30-H30) -> 585.27955 | J30: =IF(D30="","",F30-I30) -> 29522.724
... D319: =IFERROR(IF(D318+1<=$C$12,D318+1,""),"") | E319: =IF(D319="","",EOMONTH(E318,1)) | F319: =IF(D319="","",J318) | G319: =IF(D319="","",$C$13) | H319: =IF(D319="","",F319*$C$7/12) | I319: =IF(D319="","",G319-H319) | J319: =IF(D319="","",F319-I319)

Sheet Seuil de rentabilité AN1
A1: Seuil de rentabilité FT PIZZA | C1: =Paramètres!C3 -> 2025
B3: Ventes | C3: ='Trésorerie année 1'!O7+'Trésorerie année 1'!O8 -> 205146 | D3: =IF(C3='Trésorerie année 1'!O7+'Trésorerie année 1'!O8,"OK","PROB") -> OK
B4: Charges fixes | C4: ='Trésorerie année 1'!O23+'Trésorerie année 1'!O24+'Trésorerie année 1'!O25+'Trésorerie année 1'!O27+'Trésorerie année 1'!O28+'Trésorerie année 1'!O29+'Trésorerie année 1'!O30+'Trésorerie année 1'!O31+'Trésorerie année 1'!O32+'Trésorerie année 1'!O33+'Trésorerie année 1'!O34+'Trésorerie année 1'!O35+'Trésorerie année 1'!O36 -> 101467.13 | D4: =IF((C4+C5)='Trésorerie année 1'!O38,"OK","PROB") -> OK
B5: Charges variables | C5: ='Trésorerie année 1'!O18+'Trésorerie année 1'!O19+'Trésorerie année 1'!O20+'Trésorerie année 1'!O21+'Trésorerie année 1'!O22+'Trésorerie année 1'!O26 -> 85086
B7: Marge sur coûts variables | C7: =C3-C5 -> 120060
B8: Taux MCV | C8: =C7/C3 -> 0.58524173
B10: Seuil de rentabilité | C10: =C4/C8 -> 173376.45
B12: Mois | C12: Seuil de rentabilité | D12: Chiffre d'Affaires | E12: Chiffre d'Affaires cumulé | F12: Charges variables | G12: Marge Brute
B13: Janvier | C13: =$C$10 -> 173376.45 | D13: {=TRANSPOSE('Trésorerie année 1'!B7:M7)+TRANSPOSE('Trésorerie année 1'!B8:M8)} -> 18078 | E13: =D13 -> 18078 | F13: {=TRANSPOSE('Trésorerie année 1'!B18:M18)+TRANSPOSE('Trésorerie année 1'!B19:M19)+TRANSPOSE('Trésorerie année 1'!B20:M20)+TRANSPOSE('Trésorerie année 1'!B22:M22)+TRANSPOSE('Trésorerie année 1'!B21:M21)+TRANSPOSE('Trésorerie année 1'!B26:M26)} -> 7498 | G13: =D13-F13 -> 10580
B14: Février | C14: =$C$10 -> 173376.45 | D14: 15720 | E14: =D14+E13 -> 33798 | F14: 6520 | G14: =D14-F14 -> 9200
B15: Mars | C15: =$C$10 -> 173376.45 | D15: 16506 | E15: =D15+E14 -> 50304 | F15: 6846 | G15: =D15-F15 -> 9660
B16: Avril | C16: =$C$10 -> 173376.45 | D16: 17292 | E16: =D16+E15 -> 67596 | F16: 7172 | G16: =D16-F16 -> 10120
B17: Mai | C17: =$C$10 -> 173376.45 | D17: 17292 | E17: =D17+E16 -> 84888 | F17: 7172 | G17: =D17-F17 -> 10120
B18: Juin | C18: =$C$10 -> 173376.45 | D18: 16506 | E18: =D18+E17 -> 101394 | F18: 6846 | G18: =D18-F18 -> 9660
B19: Juillet | C19: =$C$10 -> 173376.45 | D19: 18078 | E19: =D19+E18 -> 119472 | F19: 7498 | G19: =D19-F19 -> 10580
B20: Août | C20: =$C$10 -> 173376.45 | D20: 16506 | E20: =D20+E19 -> 135978 | F20: 6846 | G20: =D20-F20 -> 9660
B21: Septembre | C21: =$C$10 -> 173376.45 | D21: 17292 | E21: =D21+E20 -> 153270 | F21: 7172 | G21: =D21-F21 -> 10120
B22: Octobre | C22: =$C$10 -> 173376.45 | D22: 18078 | E22: =D22+E21 -> 171348 | F22: 7498 | G22: =D22-F22 -> 10580
B23: Novembre | C23: =$C$10 -> 173376.45 | D23: 15720 | E23: =D23+E22 -> 187068 | F23: 6520 | G23: =D23-F23 -> 9200
B24: Décembre | C24: =$C$10 -> 173376.45 | D24: 18078 | E24: =D24+E23 -> 205146 | F24: 7498 | G24: =D24-F24 -> 10580

Sheet Seuil de rentabilité AN2
A1: Seuil de rentabilité FT PIZZA | C1: =Paramètres!D3 -> 2026
B3: Ventes | C3: ='Trésorerie année 2'!O7+'Trésorerie année 2'!O8 -> 236857.5 | D3: =IF(C3='Trésorerie année 2'!O7+'Trésorerie année 2'!O8,"OK","PROB") -> OK
B4: Charges fixes | C4: ='Trésorerie année 2'!O23+'Trésorerie année 2'!O24+'Trésorerie année 2'!O25+'Trésorerie année 2'!O27+'Trésorerie année 2'!O28+'Trésorerie année 2'!O29+'Trésorerie année 2'!O30+'Trésorerie année 2'!O31+'Trésorerie année 2'!O32+'Trésorerie année 2'!O33+'Trésorerie année 2'!O34+'Trésorerie année 2'!O35+'Trésorerie année 2'!O36 -> 106552.63 | D4: =IF((C4+C5)='Trésorerie année 2'!O38,"OK","PROB") -> PROB
B5: Charges variables | C5: ='Trésorerie année 2'!O18+'Trésorerie année 2'!O19+'Trésorerie année 2'!O20+'Trésorerie année 2'!O21+'Trésorerie année 2'!O22+'Trésorerie année 2'!O26 -> 100377.34
B7: Marge sur coûts variables | C7: =C3-C5 -> 136480.16
B8: Taux MCV | C8: =C7/C3 -> 0.57621212
B10: Seuil de rentabilité | C10: =C4/C8 -> 184919.11
B12: Mois | C12: Seuil de rentabilité | D12: Chiffre d'Affaires | E12: Chiffre d'Affaires cumulé | F12: Charges variables | G12: Marge Brute
B13: Janvier | C13: =$C$10 -> 184919.11 | D13: {=TRANSPOSE('Trésorerie année 2'!B7:M7)+TRANSPOSE('Trésorerie année 2'!B8:M8)} -> 19965 | E13: =D13 -> 19965 | F13: {=TRANSPOSE('Trésorerie année 2'!B18:M18)+TRANSPOSE('Trésorerie année 2'!B19:M19)+TRANSPOSE('Trésorerie année 2'!B20:M20)+TRANSPOSE('Trésorerie année 2'!B22:M22)+TRANSPOSE('Trésorerie année 2'!B21:M21)+TRANSPOSE('Trésorerie année 2'!B26:M26)} -> 8460.925 | G13: =D13-F13 -> 11504.075
B14: Février | C14: =$C$10 -> 184919.11 | D14: 18150 | E14: =D14+E13 -> 38115 | F14: 7691.75 | G14: =D14-F14 -> 10458.25
B15: Mars | C15: =$C$10 -> 184919.11 | D15: 19965 | E15: =D15+E14 -> 58080 | F15: 8460.925 | G15: =D15-F15 -> 11504.075
B16: Avril | C16: =$C$10 -> 184919.11 | D16: 19965 | E16: =D16+E15 -> 78045 | F16: 8460.925 | G16: =D16-F16 -> 11504.075
B17: Mai | C17: =$C$10 -> 184919.11 | D17: 19057.5 | E17: =D17+E16 -> 97102.5 | F17: 8076.3375 | G17: =D17-F17 -> 10981.163
B18: Juin | C18: =$C$10 -> 184919.11 | D18: 19965 | E18: =D18+E17 -> 117067.5 | F18: 8460.925 | G18: =D18-F18 -> 11504.075
B19: Juillet | C19: =$C$10 -> 184919.11 | D19: 20872.5 | E19: =D19+E18 -> 137940 | F19: 8845.5125 | G19: =D19-F19 -> 12026.988
B20: Août | C20: =$C$10 -> 184919.11 | D20: 19057.5 | E20: =D20+E19 -> 156997.5 | F20: 8076.3375 | G20: =D20-F20 -> 10981.163
B21: Septembre | C21: =$C$10 -> 184919.11 | D21: 19965 | E21: =D21+E20 -> 176962.5 | F21: 8460.925 | G21: =D21-F21 -> 11504.075
B22: Octobre | C22: =$C$10 -> 184919.11 | D22: 19965 | E22: =D22+E21 -> 196927.5 | F22: 8460.925 | G22: =D22-F22 -> 11504.075
B23: Novembre | C23: =$C$10 -> 184919.11 | D23: 19057.5 | E23: =D23+E22 -> 215985 | F23: 8076.3375 | G23: =D23-F23 -> 10981.163
B24: Décembre | C24: =$C$10 -> 184919.11 | D24: 20872.5 | E24: =D24+E23 -> 236857.5 | F24: 8845.5125 | G24: =D24-F24 -> 12026.988

Sheet Seuil de rentabilité AN3
A1: Seuil de rentabilité FT PIZZA | C1: =Paramètres!E3 -> 2027
B3: Ventes | C3: ='Trésorerie année 3'!O7+'Trésorerie année 3'!O8 -> 261022.35 | D3: =IF(C3='Trésorerie année 3'!O7+'Trésorerie année 3'!O8,"OK","PROB") -> OK
B4: Charges fixes | C4: ='Trésorerie année 3'!O23+'Trésorerie année 3'!O24+'Trésorerie année 3'!O25+'Trésorerie année 3'!O27+'Trésorerie année 3'!O28+'Trésorerie année 3'!O29+'Trésorerie année 3'!O30+'Trésorerie année 3'!O31+'Trésorerie année 3'!O32+'Trésorerie année 3'!O33+'Trésorerie année 3'!O34+'Trésorerie année 3'!O35+'Trésorerie année 3'!O36 -> 112818.81 | D4: =IF((C4+C5)='Trésorerie année 3'!O38,"OK","PROB") -> PROB
B5: Charges variables | C5: ='Trésorerie année 3'!O18+'Trésorerie année 3'!O19+'Trésorerie année 3'!O20+'Trésorerie année 3'!O21+'Trésorerie année 3'!O22+'Trésorerie année 3'!O26 -> 113040.85
B7: Marge sur coûts variables | C7: =C3-C5 -> 147981.5
B8: Taux MCV | C8: =C7/C3 -> 0.56693037
B10: Seuil de rentabilité | C10: =C4/C8 -> 198999.41
B12: Mois | C12: Seuil de rentabilité | D12: Chiffre d'Affaires | E12: Chiffre d'Affaires cumulé | F12: Charges variables | G12: Marge Brute
B13: Janvier | C13: =$C$10 -> 198999.41 | D13: {=TRANSPOSE('Trésorerie année 3'!B7:M7)+TRANSPOSE('Trésorerie année 3'!B8:M8)} -> 21001.798 | E13: =D13 -> 21001.798 | F13: {=TRANSPOSE('Trésorerie année 3'!B18:M18)+TRANSPOSE('Trésorerie année 3'!B19:M19)+TRANSPOSE('Trésorerie année 3'!B20:M20)+TRANSPOSE('Trésorerie année 3'!B22:M22)+TRANSPOSE('Trésorerie année 3'!B21:M21)+TRANSPOSE('Trésorerie année 3'!B26:M26)} -> 9095.241 | G13: =D13-F13 -> 11906.557
B14: Février | C14: =$C$10 -> 198999.41 | D14: 20001.713 | E14: =D14+E13 -> 41003.511 | F14: 8662.1343 | G14: =D14-F14 -> 11339.578
B15: Mars | C15: =$C$10 -> 198999.41 | D15: 23001.969 | E15: =D15+E14 -> 64005.48 | F15: 9961.4544 | G15: =D15-F15 -> 13040.515
B16: Avril | C16: =$C$10 -> 198999.41 | D16: 22001.884 | E16: =D16+E15 -> 86007.364 | F16: 9528.3477 | G16: =D16-F16 -> 12473.536
B17: Mai | C17: =$C$10 -> 198999.41 | D17: 21001.798 | E17: =D17+E16 -> 107009.16 | F17: 9095.241 | G17: =D17-F17 -> 11906.557
B18: Juin | C18: =$C$10 -> 198999.41 | D18: 22001.884 | E18: =D18+E17 -> 129011.05 | F18: 9528.3477 | G18: =D18-F18 -> 12473.536
B19: Juillet | C19: =$C$10 -> 198999.41 | D19: 22001.884 | E19: =D19+E18 -> 151012.93 | F19: 9528.3477 | G19: =D19-F19 -> 12473.536
B20: Août | C20: =$C$10 -> 198999.41 | D20: 22001.884 | E20: =D20+E19 -> 173014.81 | F20: 9528.3477 | G20: =D20-F20 -> 12473.536
B21: Septembre | C21: =$C$10 -> 198999.41 | D21: 22001.884 | E21: =D21+E20 -> 195016.7 | F21: 9528.3477 | G21: =D21-F21 -> 12473.536
B22: Octobre | C22: =$C$10 -> 198999.41 | D22: 21001.798 | E22: =D22+E21 -> 216018.5 | F22: 9095.241 | G22: =D22-F22 -> 11906.557
B23: Novembre | C23: =$C$10 -> 198999.41 | D23: 22001.884 | E23: =D23+E22 -> 238020.38 | F23: 9528.3477 | G23: =D23-F23 -> 12473.536
B24: Décembre | C24: =$C$10 -> 198999.41 | D24: 23001.969 | E24: =D24+E23 -> 261022.35 | F24: 9961.4544 | G24: =D24-F24 -> 13040.515

Sheet Liste matériel pizza FT
B2: Listing matériels - Camion à pizza intermédiaire
B5: Matériels | C5: Quantité | D5: HT | E5: TTC | F5: Total
B6: four pro à gaz ou élec chmabre 6-8 pizzas système vapeur programmation température et évacuation optimisée | C6: 1 | D6: 10000 | E6: =D6*1.2 -> 12000 | F6: =C6*E6 -> 12000
B7: réfrigération avancée - système réfrigération multiple zone, bacs gastro congélateur séparé autonomie 72h | C7: 1 | D7: 5415 | E7: =D7*1.2 -> 6498 | F7: =C7*E7 -> 6498
B8: aménagement pro - agencement sur mesure, inox alimentaire, poste de travail ergonomique, évier 2 bacs, rangement optimisés (saladette) | C8: 1 | D8: 7500 | E8: =D8*1.2 -> 9000 | F8: =C8*E8 -> 9000
B9: système énergétique - groupe électrogène silencieux 5-7kw batteries lithium onduleur pro, tableau électrique complet | C9: 1 | D9: 5000 | E9: =D9*1.2 -> 6000 | F9: =C9*E9 -> 6000
B10: enseigne led sonorisation clim poste de travail, éclairage client | C10: 1 | D10: 2500 | E10: =D10*1.2 -> 3000 | F10: =C10*E10 -> 3000
B11: pétrin professionnel | C11: 1 | D11: 3000 | E11: =D11*1.2 -> 3600 | F11: =C11*E11 -> 3600
B12: brosse four | C12: 1 | D12: 54 | E12: =D12*1.2 -> 64.8 | F12: =C12*E12 -> 64.8
B13: coupe pate | C13: 2 | D13: 6.5 | E13: =D13*1.2 -> 7.8 | F13: =C13*E13 -> 15.6
B14: plaques à pizza romaine | C14: 2 | D14: 35 | E14: =D14*1.2 -> 42 | F14: =C14*E14 -> 84
B15: thermomètre | C15: 1 | D15: 50 | E15: =D15*1.2 -> 60 | F15: =C15*E15 -> 60
B16: pelle à défourner | C16: 1 | D16: 93 | E16: =D16*1.2 -> 111.6 | F16: =C16*E16 -> 111.6
B17: pelle à enfourner | C17: 1 | D17: 120 | E17: =D17*1.2 -> 144 | F17: =C17*E17 -> 144
... B28: serviettes torchons | C28: 6 | D28: 10 | E28: =D28*1.2 -> 12 | F28: =C28*E28 -> 72
E29: TOTAL | F29: =SUM(F6:F28) -> 45086.4

Sheet Feuil7
A3: ='Seuil de rentabilité AN1'!A1&" "&'Seuil de rentabilité AN1'!C1 -> Seuil de rentabilité FT PIZZA 2025
A4: ='Seuil de rentabilité AN2'!A1&" "&'Seuil de rentabilité AN2'!C1 -> Seuil de rentabilité FT PIZZA 2026
A5: ='Seuil de rentabilité AN3'!A1&" "&'Seuil de rentabilité AN3'!C1 -> Seuil de rentabilité FT PIZZA 2027
